{
  "javascript": {
    "main": "/js/bundle.js"
  },
  "styles": {},
  "assets": {
    "./common/components/layouts/AppLayout/styles.scss": {
      "root": "root_2nl",
      "_style": "/* stylelint-disable */\n/* stylelint-enable */\n/* stylelint-disable */\n/* stylelint-enable */\n.root_2nl {\n  height: 100%;\n  color: #444444; }\n"
    },
    "./common/components/utils/IconBtn/styles.scss": {
      "btn": "btn_34k",
      "icon": "icon_D9Z",
      "_style": "/* stylelint-disable */\n/* stylelint-enable */\n/* stylelint-disable */\n/* stylelint-enable */\n.btn_34k {\n  font-size: 15px;\n  font-size: 0.9375rem;\n  width: 26px;\n  height: 26px;\n  padding: 0;\n  color: white;\n  border: 0;\n  background-color: transparent; }\n  .btn_34k:focus {\n    outline: 0; }\n\n.icon_D9Z {\n  background-color: transparent; }\n"
    },
    "./common/components/utils/Modal/styles.scss": {
      "modal": "modal_3Ga",
      "modal-active": "modal-active_2AM",
      "modalActive": "modal-active_2AM",
      "modal-inactive": "modal-inactive_2-Z",
      "modalInactive": "modal-inactive_2-Z",
      "dialog": "dialog_31h",
      "dialog-msg": "dialog-msg_3L7",
      "dialogMsg": "dialog-msg_3L7",
      "dialog-title": "dialog-title_30X",
      "dialogTitle": "dialog-title_30X",
      "dialog-content": "dialog-content_3EX",
      "dialogContent": "dialog-content_3EX",
      "dialog-content-msg": "dialog-content-msg_pUV",
      "dialogContentMsg": "dialog-content-msg_pUV",
      "btn-close": "btn-close_1JX",
      "btnClose": "btn-close_1JX",
      "_style": "/* stylelint-disable */\n/* stylelint-enable */\n/* stylelint-disable */\n/* stylelint-enable */\n.modal_3Ga, .modal-active_2AM, .modal-inactive_2-Z {\n  position: absolute;\n  top: 0;\n  left: 0;\n  z-index: 100000;\n  width: 100%;\n  height: 100%; }\n\n.modal-inactive_2-Z {\n  display: none; }\n\n.dialog_31h, .dialog-msg_3L7 {\n  display: -webkit-box;\n  display: -ms-flexbox;\n  display: flex;\n  -webkit-box-orient: vertical;\n  -webkit-box-direction: normal;\n      -ms-flex-direction: column;\n          flex-direction: column;\n  position: absolute;\n  top: 150px;\n  left: calc(50% - 440px / 2);\n  width: 440px;\n  padding: 30px;\n  border-radius: 10px;\n  background-color: #ffffff; }\n\n.dialog-title_30X {\n  font-size: 24px;\n  font-size: 1.5rem;\n  font-weight: 900;\n  color: #000000;\n  text-align: center; }\n\n.dialog-content_3EX, .dialog-content-msg_pUV {\n  -webkit-box-flex: 1;\n      -ms-flex: 1;\n          flex: 1;\n  margin-top: 15px; }\n\n.btn-close_1JX {\n  font-size: 20px;\n  font-size: 1.25rem;\n  position: absolute;\n  top: 15px;\n  right: 15px;\n  color: #000000 !important;\n  background-color: transparent !important; }\n\n.dialog-content-msg_pUV {\n  display: -webkit-box;\n  display: -ms-flexbox;\n  display: flex;\n  -webkit-box-orient: vertical;\n  -webkit-box-direction: normal;\n      -ms-flex-direction: column;\n          flex-direction: column;\n  -ms-flex-pack: distribute;\n      justify-content: space-around;\n  font-size: 20px;\n  font-size: 1.25rem;\n  -webkit-box-align: center;\n      -ms-flex-align: center;\n          align-items: center; }\n\n.dialog-msg_3L7 {\n  height: 250px; }\n"
    },
    "./common/components/utils/FormButton/styles.scss": {
      "btn": "btn_MlH",
      "btn-submit": "btn-submit_SPJ",
      "btnSubmit": "btn-submit_SPJ",
      "btn-button": "btn-button_3i0",
      "btnButton": "btn-button_3i0",
      "btn-fb": "btn-fb_3A9",
      "btnFb": "btn-fb_3A9",
      "_style": "/* stylelint-disable */\n/* stylelint-enable */\n/* stylelint-disable */\n/* stylelint-enable */\n.btn_MlH, .btn-submit_SPJ, .btn-button_3i0, .btn-fb_3A9 {\n  font-size: 16px;\n  font-size: 1rem;\n  width: 100px;\n  margin: 0 20px;\n  padding: 8px 0;\n  letter-spacing: 2px;\n  border: 2px solid #f78b6d;\n  border-radius: 50px; }\n\n.btn-submit_SPJ {\n  color: #ffffff;\n  background: #f78b6d; }\n\n.btn-button_3i0 {\n  color: #f78b6d;\n  background: transparent; }\n\n.btn-fb_3A9 {\n  color: #ffffff;\n  border-color: #3b5998;\n  background-color: #3b5998; }\n"
    },
    "./common/components/utils/Navigation/styles.scss": {
      "nav": "nav_VKa",
      "text": "text_1iT",
      "dropdown-text": "dropdown-text_3rr",
      "dropdownText": "dropdown-text_3rr",
      "header": "header_2qo",
      "avatar": "avatar_1z2",
      "_style": "/* stylelint-disable */\n/* stylelint-enable */\n/* stylelint-disable */\n/* stylelint-enable */\n.nav_VKa {\n  border-width: 0;\n  background-color: #666666; }\n\n.text_1iT, .dropdown-text_3rr {\n  font-size: 16px;\n  font-size: 1rem;\n  color: #ffffff; }\n\n.header_2qo {\n  margin-left: 25px; }\n\n.dropdown-text_3rr {\n  display: inline; }\n\n.avatar_1z2 {\n  width: 22px;\n  height: 22px;\n  background: transparent url(/img/default-avatar.png) no-repeat center center;\n  background-size: contain;\n  display: inline-block; }\n"
    },
    "./common/components/utils/Spinner/styles.scss": {
      "div": "div_1uN",
      "dot": "dot_2Jc",
      "one": "one_YEN",
      "two": "two_2me",
      "three": "three_21s",
      "bouncedelay": "bouncedelay_2_Y",
      "_style": "/* stylelint-disable */\n/* stylelint-enable */\n/* stylelint-disable */\n/* stylelint-enable */\n@-webkit-keyframes bouncedelay_2_Y {\n  0%, 80%, 100% {\n    -webkit-transform: scale(0);\n            transform: scale(0); }\n  40% {\n    -webkit-transform: scale(1);\n            transform: scale(1); } }\n@keyframes bouncedelay_2_Y {\n  0%, 80%, 100% {\n    -webkit-transform: scale(0);\n            transform: scale(0); }\n  40% {\n    -webkit-transform: scale(1);\n            transform: scale(1); } }\n\n.div_1uN {\n  display: -webkit-box;\n  display: -ms-flexbox;\n  display: flex;\n  -webkit-box-orient: horizontal;\n  -webkit-box-direction: normal;\n      -ms-flex-direction: row;\n          flex-direction: row;\n  -webkit-box-pack: justify;\n      -ms-flex-pack: justify;\n          justify-content: space-between; }\n\n.dot_2Jc, .one_YEN, .two_2me, .three_21s {\n  border-radius: 100%;\n  background-color: #ffffff;\n  -webkit-user-select: none;\n     -moz-user-select: none;\n      -ms-user-select: none;\n          user-select: none;\n  -webkit-animation: bouncedelay_2_Y 1.3s infinite ease-in-out both;\n          animation: bouncedelay_2_Y 1.3s infinite ease-in-out both; }\n\n.one_YEN {\n  -webkit-animation-delay: -0.32s;\n          animation-delay: -0.32s; }\n\n.two_2me {\n  -webkit-animation-delay: -0.16s;\n          animation-delay: -0.16s; }\n"
    },
    "./common/components/fields/widgets/DField/styles.scss": {
      "container": "container_1pK",
      "label-div": "label-div_2eU",
      "labelDiv": "label-div_2eU",
      "label": "label_m46",
      "error": "error_37-",
      "_style": "/* stylelint-disable */\n/* stylelint-enable */\n/* stylelint-disable */\n/* stylelint-enable */\n.container_1pK {\n  font-size: 16px;\n  font-size: 1rem;\n  margin: 20px 0 10px;\n  color: #ffffff; }\n\n.label-div_2eU {\n  display: -webkit-box;\n  display: -ms-flexbox;\n  display: flex;\n  -webkit-box-orient: horizontal;\n  -webkit-box-direction: normal;\n      -ms-flex-direction: row;\n          flex-direction: row;\n  -webkit-box-pack: justify;\n      -ms-flex-pack: justify;\n          justify-content: space-between;\n  margin: 10px 0; }\n\n.label_m46 {\n  font-size: 16px;\n  font-size: 1rem;\n  color: #ffffff;\n  letter-spacing: 2px; }\n\n.error_37- {\n  color: #ff0000;\n  text-align: center; }\n"
    },
    "./common/components/forms/user/RegisterForm/styles.scss": {
      "bg": "bg_p6o",
      "title": "title_1_E",
      "content": "content_327",
      "line": "line_2j4",
      "checkbox": "checkbox_O2X",
      "footer": "footer_1IQ",
      "error": "error_PkD",
      "spinner": "spinner_2JH",
      "spinner-dot": "spinner-dot_Z11",
      "spinnerDot": "spinner-dot_Z11",
      "agreement": "agreement_wy2",
      "_style": "/* stylelint-disable */\n/* stylelint-enable */\n/* stylelint-disable */\n/* stylelint-enable */\n.bg_p6o {\n  border-radius: 5px;\n  background-color: rgba(34, 34, 34, 0.55); }\n\n.title_1_E {\n  font-size: 20px;\n  font-size: 1.25rem;\n  padding: 20px;\n  color: #ffffff;\n  text-align: center;\n  border-bottom: 1px solid #cccccc; }\n\n.content_327 {\n  padding: 30px 40px 20px; }\n\n.line_2j4 {\n  margin: 20px 0;\n  border: 0;\n  border-top: 1px solid #f0f0f0; }\n\n.checkbox_O2X {\n  color: #ffffff; }\n\n.footer_1IQ {\n  display: -webkit-box;\n  display: -ms-flexbox;\n  display: flex;\n  -webkit-box-pack: center;\n      -ms-flex-pack: center;\n          justify-content: center;\n  -webkit-box-align: center;\n      -ms-flex-align: center;\n          align-items: center;\n  width: 100%;\n  padding: 10px 0; }\n\n.error_PkD {\n  color: #ff0000; }\n\n.spinner_2JH {\n  position: absolute;\n  left: calc(50% + 75px); }\n\n.spinner-dot_Z11 {\n  background-color: #f78b6d !important; }\n\n.agreement_wy2 {\n  margin: 0 0 15px !important;\n  padding: 0 5px !important;\n  color: #ffffff !important; }\n"
    },
    "./common/container/user/RegisterPage/styles.scss": {
      "form": "form_1x5",
      "_style": ".form_1x5 {\n  margin-top: 55px; }\n"
    },
    "./common/components/forms/user/LoginForm/styles.scss": {
      "bg": "bg_3WB",
      "title": "title_1ED",
      "line": "line_2BW",
      "content": "content_1w_",
      "checkbox": "checkbox_4AY",
      "footer": "footer_2eE",
      "error": "error_1nO",
      "_style": "/* stylelint-disable */\n/* stylelint-enable */\n/* stylelint-disable */\n/* stylelint-enable */\n.bg_3WB {\n  border-radius: 5px;\n  background-color: rgba(34, 34, 34, 0.55); }\n\n.title_1ED {\n  font-size: 20px;\n  font-size: 1.25rem;\n  padding: 20px;\n  color: #ffffff;\n  text-align: center;\n  border-bottom: 1px solid #cccccc; }\n\n.line_2BW {\n  margin: 20px 0;\n  border: 0;\n  border-top: 1px solid #f0f0f0; }\n\n.content_1w_ {\n  padding: 30px 40px 20px; }\n\n.checkbox_4AY {\n  margin: 0 0 15px !important;\n  padding: 0 5px !important;\n  color: #ffffff !important; }\n\n.footer_2eE {\n  display: -webkit-box;\n  display: -ms-flexbox;\n  display: flex;\n  -webkit-box-pack: center;\n      -ms-flex-pack: center;\n          justify-content: center;\n  -webkit-box-align: center;\n      -ms-flex-align: center;\n          align-items: center;\n  width: 100%;\n  padding: 10px 0; }\n\n.error_1nO {\n  color: #ff0000; }\n"
    },
    "./common/container/user/LoginPage/styles.scss": {
      "form": "form_3L0",
      "_style": ".form_3L0 {\n  margin-top: 55px; }\n"
    },
    "./common/container/memberCenter/PersonalDataPage/styles.scss": {
      "avatar": "avatar_BUm",
      "panel1": "panel1_1gS",
      "hr": "hr_1V3",
      "header": "header_kKt",
      "_style": "/* stylelint-disable */\n/* stylelint-enable */\n/* stylelint-disable */\n/* stylelint-enable */\n.avatar_BUm {\n  width: 100%;\n  height: auto;\n  border-radius: 50%; }\n\n.panel1_1gS {\n  padding-left: 0; }\n\n.hr_1V3 {\n  height: 1px !important;\n  background-color: #f78b6d !important; }\n\n.header_kKt {\n  font-size: 20px;\n  font-size: 1.25rem;\n  padding-top: 10px;\n  color: #f78b6d; }\n"
    },
    "./common/components/utils/Panel/styles.scss": {
      "underline": "underline_3Rx",
      "container": "container_1Ne",
      "title": "title_3tx",
      "content-div": "content-div_1De",
      "contentDiv": "content-div_1De",
      "comment": "comment_2ja",
      "underline1": "underline1_bxX",
      "title1": "title1_3Je",
      "content-div1": "content-div1_1M7",
      "contentDiv1": "content-div1_1M7",
      "underline2": "underline2_3yu",
      "panel-with-word": "panel-with-word_1HN",
      "panelWithWord": "panel-with-word_1HN",
      "underline-with-word": "underline-with-word_2_O",
      "underlineWithWord": "underline-with-word_2_O",
      "title-with-word": "title-with-word_1Uc",
      "titleWithWord": "title-with-word_1Uc",
      "content-div-with-word": "content-div-with-word_1yp",
      "contentDivWithWord": "content-div-with-word_1yp",
      "comment-with-word": "comment-with-word_eOc",
      "commentWithWord": "comment-with-word_eOc",
      "_style": "/* stylelint-disable */\n/* stylelint-enable */\n/* stylelint-disable */\n/* stylelint-enable */\n.underline_3Rx {\n  width: 90%;\n  height: 2px;\n  margin: 0 auto; }\n\n.container_1Ne {\n  margin-bottom: 20px;\n  border-radius: 5px;\n  background-color: #ffffff; }\n\n.title_3tx {\n  font-size: 20px;\n  font-size: 1.25rem;\n  padding: 20px 30px;\n  color: #f78b6d;\n  text-align: center; }\n\n.content-div_1De {\n  padding: 20px 15px; }\n\n.comment_2ja {\n  font-size: 15px;\n  font-size: 0.9375rem;\n  color: #000000; }\n\n/* Panel1 */\n.underline1_bxX {\n  height: 3px;\n  background-color: #f78b6d; }\n\n.title1_3Je {\n  text-align: left; }\n\n.content-div1_1M7 {\n  padding: 20px 30px; }\n\n/* Panel2 */\n.underline2_3yu {\n  background-color: #cccccc; }\n\n/* PanelWithWord */\n.panel-with-word_1HN {\n  padding: 20px 30px; }\n\n.underline-with-word_2_O {\n  display: none; }\n\n.title-with-word_1Uc {\n  font-size: 22px;\n  font-size: 1.375rem;\n  padding: 20px 20px 15px;\n  color: #000000;\n  text-align: center; }\n\n.content-div-with-word_1yp {\n  margin: 20px 0; }\n\n.comment-with-word_eOc {\n  width: 75%;\n  margin: 0 auto;\n  line-height: 22px;\n  color: #000000;\n  text-align: center;\n  letter-spacing: 1px; }\n"
    },
    "./common/components/utils/PanelContainer/styles.scss": {
      "container": "container_D11",
      "_style": ".container_D11 {\n  padding: 25px; }\n"
    },
    "./common/components/utils/SubNavigation/styles.scss": {
      "nav": "nav_1db",
      "header": "header_2tJ",
      "text": "text_3yF",
      "text-active": "text-active_3z4",
      "textActive": "text-active_3z4",
      "text-inactive": "text-inactive_a2q",
      "textInactive": "text-inactive_a2q",
      "_style": "/* stylelint-disable */\n/* stylelint-enable */\n/* stylelint-disable */\n/* stylelint-enable */\n.nav_1db {\n  z-index: 0;\n  border-width: 0;\n  background-color: #ffffff; }\n\n.header_2tJ {\n  margin-left: 20px; }\n\n.text_3yF, .text-active_3z4, .text-inactive_a2q {\n  font-size: 16px;\n  font-size: 1rem; }\n\n.text-active_3z4 {\n  color: #f78b6d; }\n\n.text-inactive_a2q {\n  color: #000000; }\n"
    },
    "./common/components/utils/FormFooter/styles.scss": {
      "container": "container_2Qe",
      "_style": "/* stylelint-disable */\n/* stylelint-enable */\n/* stylelint-disable */\n/* stylelint-enable */\n.container_2Qe {\n  display: -webkit-box;\n  display: -ms-flexbox;\n  display: flex;\n  -webkit-box-pack: center;\n      -ms-flex-pack: center;\n          justify-content: center;\n  -webkit-box-align: center;\n      -ms-flex-align: center;\n          align-items: center;\n  margin: 10px 0 15px; }\n"
    },
    "./common/components/forms/trip/PhaseTripBranch/styles.scss": {
      "container": "container_2S9",
      "site-div": "site-div_2SL",
      "siteDiv": "site-div_2SL",
      "msg-error": "msg-error_1Du",
      "msgError": "msg-error_1Du",
      "site-div-btn": "site-div-btn_2Dc",
      "siteDivBtn": "site-div-btn_2Dc",
      "site-div-msg": "site-div-msg_3hF",
      "siteDivMsg": "site-div-msg_3hF",
      "site-div-btn-div": "site-div-btn-div_15x",
      "siteDivBtnDiv": "site-div-btn-div_15x",
      "float-site-list-container": "float-site-list-container_3kU",
      "floatSiteListContainer": "float-site-list-container_3kU",
      "float-site-list": "float-site-list_3iX",
      "floatSiteList": "float-site-list_3iX",
      "float-site-list-item": "float-site-list-item_rnN",
      "floatSiteListItem": "float-site-list-item_rnN",
      "float-site-list-item-name": "float-site-list-item-name_2Q3",
      "floatSiteListItemName": "float-site-list-item-name_2Q3",
      "float-site-list-item-icon": "float-site-list-item-icon_Hf8",
      "floatSiteListItemIcon": "float-site-list-item-icon_Hf8",
      "float-site-list-title-div": "float-site-list-title-div_3Nz",
      "floatSiteListTitleDiv": "float-site-list-title-div_3Nz",
      "float-site-list-title": "float-site-list-title_3KI",
      "floatSiteListTitle": "float-site-list-title_3KI",
      "float-site-list-icon": "float-site-list-icon_1tx",
      "floatSiteListIcon": "float-site-list-icon_1tx",
      "dropdown": "dropdown_uiL",
      "day-div": "day-div_3dq",
      "dayDiv": "day-div_3dq",
      "day-div-btn": "day-div-btn_2RN",
      "dayDivBtn": "day-div-btn_2RN",
      "day-div-btn-div": "day-div-btn-div_1w8",
      "dayDivBtnDiv": "day-div-btn-div_1w8",
      "footer": "footer_2y3",
      "float-info-subtitle": "float-info-subtitle_2X-",
      "floatInfoSubtitle": "float-info-subtitle_2X-",
      "which-day": "which-day_8ud",
      "whichDay": "which-day_8ud",
      "choose-day-div": "choose-day-div_3gB",
      "chooseDayDiv": "choose-day-div_3gB",
      "_style": "/* stylelint-disable */\n/* stylelint-enable */\n/* stylelint-disable */\n/* stylelint-enable */\n.container_2S9 {\n  position: relative;\n  overflow-y: scroll;\n  width: 100%;\n  height: 600px;\n  border: 2px solid #cccccc;\n  border-radius: 10px; }\n\n.site-div_2SL {\n  position: absolute;\n  padding: 5px 10px;\n  font-weight: bold;\n  border: 2px solid #444444;\n  border-radius: 5px;\n  background: white; }\n\n.msg-error_1Du {\n  font-size: 16px;\n  font-size: 1rem;\n  width: 100%;\n  margin: 0 0 15px;\n  color: #ff0000;\n  text-align: right; }\n\n.site-div-btn_2Dc {\n  font-size: 20px;\n  font-size: 1.25rem;\n  display: inline-block;\n  margin: 0 3px;\n  color: #f78b6d !important; }\n\n.site-div-msg_3hF {\n  font-size: 14px;\n  font-size: 0.875rem;\n  margin: 3px 0; }\n\n.site-div-btn-div_15x {\n  position: absolute;\n  right: 5px;\n  bottom: 5px; }\n\n.float-site-list-container_3kU {\n  display: -webkit-box;\n  display: -ms-flexbox;\n  display: flex;\n  -webkit-box-orient: horizontal;\n  -webkit-box-direction: normal;\n      -ms-flex-direction: row;\n          flex-direction: row;\n  -webkit-box-align: center;\n      -ms-flex-align: center;\n          align-items: center;\n  height: 26px; }\n\n.float-site-list_3iX {\n  position: absolute;\n  z-index: 100;\n  overflow-y: scroll;\n  width: 240px;\n  height: 320px;\n  padding: 5px;\n  border: 10px solid #777777;\n  border-radius: 10px;\n  background: white; }\n\n.float-site-list-item_rnN {\n  display: -webkit-box;\n  display: -ms-flexbox;\n  display: flex;\n  overflow-x: hidden;\n  -webkit-box-orient: horizontal;\n  -webkit-box-direction: normal;\n      -ms-flex-direction: row;\n          flex-direction: row;\n  -webkit-box-pack: start;\n      -ms-flex-pack: start;\n          justify-content: flex-start;\n  -webkit-box-align: center;\n      -ms-flex-align: center;\n          align-items: center;\n  -ms-flex-line-pack: center;\n      align-content: center;\n  width: 100%;\n  height: 50px;\n  padding: 5px;\n  border: 1px none #cccccc;\n  border-bottom-style: solid;\n  cursor: pointer; }\n  .float-site-list-item_rnN:hover {\n    background-color: #f0f0f0; }\n\n.float-site-list-item-name_2Q3 {\n  font-size: 16px;\n  font-size: 1rem; }\n\n.float-site-list-item-icon_Hf8 {\n  font-size: 16px;\n  font-size: 1rem;\n  margin-right: 10px;\n  color: #f78b6d !important; }\n\n.float-site-list-title-div_3Nz {\n  display: -webkit-box;\n  display: -ms-flexbox;\n  display: flex;\n  -webkit-box-orient: horizontal;\n  -webkit-box-direction: normal;\n      -ms-flex-direction: row;\n          flex-direction: row;\n  -webkit-box-align: center;\n      -ms-flex-align: center;\n          align-items: center;\n  height: 26px; }\n\n.float-site-list-title_3KI {\n  font-size: 16px;\n  font-size: 1rem;\n  -webkit-box-flex: 1;\n      -ms-flex: 1;\n          flex: 1;\n  margin-left: 5px; }\n\n.float-site-list-icon_1tx {\n  font-size: 22px !important;\n  font-size: 1.375rem !important;\n  float: right;\n  color: #777777 !important;\n  background-color: #ffffff !important; }\n\n.dropdown_uiL {\n  font-size: 20px;\n  font-size: 1.25rem;\n  position: relative;\n  list-style: none; }\n\n.day-div_3dq {\n  display: -webkit-box;\n  display: -ms-flexbox;\n  display: flex;\n  -webkit-box-orient: horizontal;\n  -webkit-box-direction: normal;\n      -ms-flex-direction: row;\n          flex-direction: row;\n  -webkit-box-pack: justify;\n      -ms-flex-pack: justify;\n          justify-content: space-between;\n  -webkit-box-align: center;\n      -ms-flex-align: center;\n          align-items: center;\n  margin: 10px 0; }\n\n.day-div-btn_2RN {\n  display: inline-block;\n  margin: 0 8px;\n  color: #f78b6d;\n  border: solid 2px #f78b6d;\n  border-radius: 20px; }\n\n.day-div-btn-div_1w8 {\n  margin: 0 10px; }\n\n.footer_2y3 {\n  display: -webkit-box;\n  display: -ms-flexbox;\n  display: flex;\n  -webkit-box-orient: vertical;\n  -webkit-box-direction: normal;\n      -ms-flex-direction: column;\n          flex-direction: column;\n  -webkit-box-align: center;\n      -ms-flex-align: center;\n          align-items: center;\n  margin: 20px 0 0; }\n\n.float-info-subtitle_2X- {\n  font-size: 16px;\n  font-size: 1rem;\n  -webkit-box-flex: 1;\n      -ms-flex: 1;\n          flex: 1;\n  margin-left: 5px; }\n\n.which-day_8ud {\n  font-size: 20px;\n  font-size: 1.25rem; }\n\n.choose-day-div_3gB {\n  display: -webkit-box;\n  display: -ms-flexbox;\n  display: flex;\n  -webkit-box-orient: horizontal;\n  -webkit-box-direction: normal;\n      -ms-flex-direction: row;\n          flex-direction: row;\n  -webkit-box-align: center;\n      -ms-flex-align: center;\n          align-items: center; }\n"
    },
    "./common/components/forms/trip/PhasePic/styles.scss": {
      "title": "title_3xM",
      "gallery": "gallery_1FL",
      "add-cover-pic": "add-cover-pic_3xx",
      "addCoverPic": "add-cover-pic_3xx",
      "add-cover-pic-btn": "add-cover-pic-btn_AHm",
      "addCoverPicBtn": "add-cover-pic-btn_AHm",
      "pic": "pic_3wd",
      "_style": "/* stylelint-disable */\n/* stylelint-enable */\n/* stylelint-disable */\n/* stylelint-enable */\n.title_3xM {\n  margin-bottom: 15px;\n  padding: 5px 20px;\n  color: #f78b6d;\n  text-align: left;\n  border-left: 5px #f78b6d solid;\n  background-color: #ffffff; }\n\n.gallery_1FL {\n  display: -webkit-box;\n  display: -ms-flexbox;\n  display: flex;\n  -webkit-box-orient: horizontal;\n  -webkit-box-direction: normal;\n      -ms-flex-direction: row;\n          flex-direction: row;\n  margin-bottom: 20px; }\n\n.add-cover-pic_3xx, .add-cover-pic-btn_AHm {\n  display: -webkit-box;\n  display: -ms-flexbox;\n  display: flex;\n  -webkit-box-pack: center;\n      -ms-flex-pack: center;\n          justify-content: center;\n  -webkit-box-align: center;\n      -ms-flex-align: center;\n          align-items: center;\n  overflow: hidden;\n  width: 140px;\n  height: 105px;\n  margin: 0 5px;\n  color: #f78b6d; }\n  .add-cover-pic_3xx:hover, .add-cover-pic-btn_AHm:hover {\n    background-color: #f0f0f0; }\n\n.pic_3wd {\n  width: 100%; }\n\n.add-cover-pic-btn_AHm {\n  border: 2px #dddddd solid;\n  cursor: pointer; }\n  .add-cover-pic-btn_AHm:hover {\n    background-color: #f0f0f0; }\n"
    },
    "./common/components/forms/trip/PhaseDone/styles.scss": {
      "container": "container_1Zp",
      "img-done": "img-done_3LD",
      "imgDone": "img-done_3LD",
      "comment": "comment_374",
      "btn": "btn_2RU",
      "_style": "/* stylelint-disable */\n/* stylelint-enable */\n/* stylelint-disable */\n/* stylelint-enable */\n.container_1Zp {\n  display: -webkit-box;\n  display: -ms-flexbox;\n  display: flex;\n  -webkit-box-orient: vertical;\n  -webkit-box-direction: normal;\n      -ms-flex-direction: column;\n          flex-direction: column;\n  -webkit-box-align: center;\n      -ms-flex-align: center;\n          align-items: center;\n  padding: 20px; }\n\n.img-done_3LD {\n  width: 150px;\n  height: 150px;\n  background: transparent url(/img/createsitepage/icon_finish.png) no-repeat center center;\n  background-size: contain;\n  margin: 0 auto 30px; }\n\n.comment_374 {\n  font-size: 16px;\n  font-size: 1rem;\n  margin-bottom: 30px; }\n\n.btn_2RU {\n  width: auto;\n  padding: 8px 20px; }\n"
    },
    "./common/components/utils/PhaseBranch/styles.scss": {
      "node-wrapper": "node-wrapper_jQX",
      "nodeWrapper": "node-wrapper_jQX",
      "node-label-div": "node-label-div_CxB",
      "nodeLabelDiv": "node-label-div_CxB",
      "node-label": "node-label_1NQ",
      "nodeLabel": "node-label_1NQ",
      "node-label-active": "node-label-active_1Ua",
      "nodeLabelActive": "node-label-active_1Ua",
      "node-label-inactive": "node-label-inactive_1Ne",
      "nodeLabelInactive": "node-label-inactive_1Ne",
      "btn-div": "btn-div_2mh",
      "btnDiv": "btn-div_2mh",
      "btn": "btn_SFJ",
      "btn-inactive": "btn-inactive_2bl",
      "btnInactive": "btn-inactive_2bl",
      "btn-active": "btn-active_1Ta",
      "btnActive": "btn-active_1Ta",
      "stick": "stick_37L",
      "check": "check_khD",
      "check-inactive": "check-inactive_2l0",
      "checkInactive": "check-inactive_2l0",
      "check-active": "check-active_3s9",
      "checkActive": "check-active_3s9",
      "_style": "/* stylelint-disable */\n/* stylelint-enable */\n/* stylelint-disable */\n/* stylelint-enable */\n.node-wrapper_jQX {\n  display: -webkit-box;\n  display: -ms-flexbox;\n  display: flex;\n  -webkit-box-pack: center;\n      -ms-flex-pack: center;\n          justify-content: center;\n  -webkit-box-align: center;\n      -ms-flex-align: center;\n          align-items: center;\n  -webkit-box-orient: horizontal;\n  -webkit-box-direction: normal;\n      -ms-flex-direction: row;\n          flex-direction: row;\n  -webkit-box-align: start;\n      -ms-flex-align: start;\n          align-items: flex-start;\n  padding: 10px 0; }\n\n.node-label-div_CxB {\n  -webkit-box-flex: 3;\n      -ms-flex: 3;\n          flex: 3; }\n\n.node-label_1NQ, .node-label-active_1Ua, .node-label-inactive_1Ne {\n  font-size: 16px;\n  font-size: 1rem;\n  text-align: right; }\n\n.node-label-active_1Ua {\n  color: #f78b6d; }\n\n.node-label-inactive_1Ne {\n  color: #cccccc; }\n\n.btn-div_2mh {\n  display: -webkit-box;\n  display: -ms-flexbox;\n  display: flex;\n  -webkit-box-orient: vertical;\n  -webkit-box-direction: normal;\n      -ms-flex-direction: column;\n          flex-direction: column;\n  -webkit-box-align: end;\n      -ms-flex-align: end;\n          align-items: flex-end;\n  position: relative;\n  -webkit-box-flex: 1;\n      -ms-flex: 1;\n          flex: 1; }\n\n.btn_SFJ, .btn-inactive_2bl, .btn-active_1Ta {\n  width: 12px;\n  height: 12px;\n  padding: 0;\n  border: 0;\n  border-radius: 50%;\n  background-color: #cccccc; }\n\n.btn-inactive_2bl {\n  background-color: #cccccc; }\n\n.btn-active_1Ta {\n  background-color: #f78b6d; }\n\n.stick_37L {\n  position: absolute;\n  top: 5px;\n  right: 4.5px;\n  width: 3px;\n  background-color: #cccccc; }\n\n.check_khD, .check-inactive_2l0, .check-active_3s9 {\n  font-size: 20px;\n  font-size: 1.25rem;\n  position: relative;\n  top: -2px;\n  left: -4px;\n  width: 12px;\n  height: 12px;\n  padding: 0; }\n\n.check-inactive_2l0 {\n  opacity: 0; }\n\n.check-active_3s9 {\n  color: #9acd32; }\n"
    },
    "./common/components/utils/GalleryPic/styles.scss": {
      "pic-div": "pic-div_3pE",
      "picDiv": "pic-div_3pE",
      "pic": "pic_A2g",
      "filter": "filter_2nw",
      "iconbtn-remove": "iconbtn-remove_3uD",
      "iconbtnRemove": "iconbtn-remove_3uD",
      "iconbtn-div": "iconbtn-div_37L",
      "iconbtnDiv": "iconbtn-div_37L",
      "iconbtn": "iconbtn_3Z2",
      "iconbtn-pencil": "iconbtn-pencil_2PN",
      "iconbtnPencil": "iconbtn-pencil_2PN",
      "iconbtn-camera": "iconbtn-camera_3RE",
      "iconbtnCamera": "iconbtn-camera_3RE",
      "textarea-div": "textarea-div_uWD",
      "textareaDiv": "textarea-div_uWD",
      "iconbtn-close-textarea": "iconbtn-close-textarea_1P2",
      "iconbtnCloseTextarea": "iconbtn-close-textarea_1P2",
      "textarea": "textarea_JCW",
      "_style": "/* stylelint-disable */\n/* stylelint-enable */\n/* stylelint-disable */\n/* stylelint-enable */\n.pic-div_3pE {\n  display: -webkit-box;\n  display: -ms-flexbox;\n  display: flex;\n  -webkit-box-orient: vertical;\n  -webkit-box-direction: normal;\n      -ms-flex-direction: column;\n          flex-direction: column;\n  -webkit-box-align: center;\n      -ms-flex-align: center;\n          align-items: center;\n  position: relative;\n  overflow: hidden;\n  width: 140px;\n  height: 105px;\n  color: #f78b6d;\n  border: solid 1px #dddddd; }\n\n.pic_A2g {\n  width: 100%; }\n\n.filter_2nw {\n  position: absolute;\n  top: 0;\n  right: 0;\n  bottom: 0;\n  left: 0;\n  z-index: 100;\n  background-color: transparent;\n  -webkit-transition-duration: 0.3s;\n          transition-duration: 0.3s;\n  opacity: 0; }\n  .filter_2nw:hover {\n    background-color: rgba(0, 0, 0, 0.5);\n    -webkit-transition-duration: 0.3s;\n            transition-duration: 0.3s;\n    opacity: 1; }\n\n.iconbtn-remove_3uD {\n  font-size: 16px;\n  font-size: 1rem;\n  position: absolute;\n  top: 8px;\n  right: 8px;\n  color: #ffffff;\n  background: transparent;\n  cursor: pointer;\n  -webkit-user-select: none;\n     -moz-user-select: none;\n      -ms-user-select: none;\n          user-select: none; }\n\n.iconbtn-div_37L {\n  display: -webkit-box;\n  display: -ms-flexbox;\n  display: flex;\n  -webkit-box-orient: horizontal;\n  -webkit-box-direction: normal;\n      -ms-flex-direction: row;\n          flex-direction: row;\n  -webkit-box-pack: end;\n      -ms-flex-pack: end;\n          justify-content: flex-end;\n  position: absolute;\n  right: 0;\n  bottom: 0;\n  z-index: 100;\n  width: 100%;\n  height: 46px;\n  padding: 8px 5px; }\n\n.iconbtn_3Z2, .iconbtn-pencil_2PN, .iconbtn-camera_3RE {\n  display: -webkit-box !important;\n  display: -ms-flexbox !important;\n  display: flex !important;\n  -webkit-box-pack: center !important;\n      -ms-flex-pack: center !important;\n          justify-content: center !important;\n  -webkit-box-align: center !important;\n      -ms-flex-align: center !important;\n          align-items: center !important;\n  width: 30px;\n  height: 30px;\n  margin: 0 5px;\n  color: #ffffff;\n  border-radius: 100%;\n  background: #f99e85;\n  cursor: pointer;\n  -webkit-user-select: none;\n     -moz-user-select: none;\n      -ms-user-select: none;\n          user-select: none; }\n  .iconbtn_3Z2:hover, .iconbtn-pencil_2PN:hover, .iconbtn-camera_3RE:hover {\n    color: #dddddd;\n    background: #f78b6d; }\n\n.textarea-div_uWD {\n  display: -webkit-box;\n  display: -ms-flexbox;\n  display: flex;\n  -webkit-box-orient: vertical;\n  -webkit-box-direction: normal;\n      -ms-flex-direction: column;\n          flex-direction: column;\n  display: flex;\n  height: 100%;\n  border: none 1px #dddddd; }\n\n.iconbtn-close-textarea_1P2 {\n  font-size: 16px;\n  font-size: 1rem;\n  display: -webkit-box;\n  display: -ms-flexbox;\n  display: flex;\n  -webkit-box-pack: center;\n      -ms-flex-pack: center;\n          justify-content: center;\n  -webkit-box-align: center;\n      -ms-flex-align: center;\n          align-items: center;\n  position: absolute;\n  top: 0;\n  right: 0;\n  z-index: 100;\n  width: 22px;\n  height: 22px;\n  color: #aaaaaa;\n  background: #ffffff;\n  cursor: pointer; }\n\n.textarea_JCW {\n  -webkit-box-flex: 1;\n      -ms-flex: 1;\n          flex: 1;\n  padding-left: 5px;\n  color: #000;\n  color: initial;\n  border: none !important;\n  box-shadow: none !important; }\n  .textarea_JCW:focus {\n    outline: 0; }\n"
    },
    "./common/components/forms/trip/AddRemind/styles.scss": {
      "container": "container_3vG",
      "gallery": "gallery_x-8",
      "_style": "/* stylelint-disable */\n/* stylelint-enable */\n/* stylelint-disable */\n/* stylelint-enable */\n.container_3vG {\n  display: -webkit-box;\n  display: -ms-flexbox;\n  display: flex;\n  -webkit-box-orient: vertical;\n  -webkit-box-direction: normal;\n      -ms-flex-direction: column;\n          flex-direction: column;\n  -webkit-box-align: center;\n      -ms-flex-align: center;\n          align-items: center; }\n\n.gallery_x-8 {\n  width: 180px !important;\n  height: 135px !important; }\n"
    },
    "./common/components/utils/Editor/styles.scss": {
      "editor-root": "editor-root_12x",
      "editorRoot": "editor-root_12x",
      "editor-editor": "editor-editor_1WM",
      "editorEditor": "editor-editor_1WM",
      "toolbar": "toolbar_23c",
      "btn-photo": "btn-photo_1PS",
      "btnPhoto": "btn-photo_1PS",
      "btn-fa": "btn-fa_2d8",
      "btnFa": "btn-fa_2d8",
      "btn": "btn_21M",
      "btn-active": "btn-active_l0W",
      "btnActive": "btn-active_l0W",
      "btn-inactive": "btn-inactive_zRg",
      "btnInactive": "btn-inactive_zRg",
      "block-line": "block-line_2xl",
      "blockLine": "block-line_2xl",
      "style-img-quote": "style-img-quote_3Xo",
      "styleImgQuote": "style-img-quote_3Xo",
      "_style": "/* stylelint-disable */\n/* stylelint-enable */\n/* stylelint-disable */\n/* stylelint-enable */\n.editor-root_12x {\n  padding: 10px 15px;\n  font-size: 14px;\n  border: 1px solid #ddd;\n  background: #ffffff; }\n\n.editor-editor_1WM {\n  margin-top: 10px;\n  font-size: 16px;\n  border-top: 1px solid #ddd;\n  cursor: text; }\n\n.toolbar_23c {\n  display: -webkit-box;\n  display: -ms-flexbox;\n  display: flex;\n  -webkit-box-orient: horizontal;\n  -webkit-box-direction: normal;\n      -ms-flex-direction: row;\n          flex-direction: row;\n  -webkit-box-align: center;\n      -ms-flex-align: center;\n          align-items: center;\n  width: 100%;\n  margin-bottom: 5px;\n  font-size: 14px;\n  text-align: center;\n  -webkit-user-select: none;\n     -moz-user-select: none;\n      -ms-user-select: none;\n          user-select: none; }\n\n.btn-photo_1PS {\n  display: -webkit-box;\n  display: -ms-flexbox;\n  display: flex;\n  -webkit-box-pack: center;\n      -ms-flex-pack: center;\n          justify-content: center;\n  -webkit-box-align: center;\n      -ms-flex-align: center;\n          align-items: center;\n  width: 18px;\n  height: 18px;\n  margin: 0 5px;\n  color: #999999;\n  cursor: pointer; }\n\n.btn-fa_2d8 {\n  font-size: 14px;\n  font-size: 0.875rem; }\n  .btn-fa_2d8:before {\n    vertical-align: middle; }\n\n.btn_21M, .btn-active_l0W, .btn-inactive_zRg {\n  display: -webkit-box;\n  display: -ms-flexbox;\n  display: flex;\n  -webkit-box-pack: center;\n      -ms-flex-pack: center;\n          justify-content: center;\n  -webkit-box-align: center;\n      -ms-flex-align: center;\n          align-items: center;\n  width: 18px;\n  height: 18px;\n  margin: 0 5px;\n  cursor: pointer; }\n  .btn_21M:focus, .btn-active_l0W:focus, .btn-inactive_zRg:focus {\n    outline: 0; }\n\n.btn-active_l0W {\n  color: #1090ff !important; }\n\n.btn-inactive_zRg {\n  color: #999999 !important; }\n\n.block-line_2xl {\n  width: 1px;\n  height: 20px;\n  margin: 0 5px;\n  background-color: #999999; }\n\n.style-img-quote_3Xo {\n  font-size: 14px;\n  font-size: 0.875rem;\n  margin-top: 5px;\n  font-style: italic;\n  color: #999999;\n  text-align: center; }\n"
    },
    "./common/components/forms/site/PhaseIntro/styles.scss": {
      "footer": "footer_1lF",
      "option-label": "option-label_3jS",
      "optionLabel": "option-label_3jS",
      "_style": "/* stylelint-disable */\n/* stylelint-enable */\n/* stylelint-disable */\n/* stylelint-enable */\n.footer_1lF {\n  margin: 40px 0; }\n\n.option-label_3jS {\n  font-size: 15px;\n  font-size: 0.9375rem;\n  margin-bottom: 10px;\n  font-weight: 700; }\n"
    },
    "./common/components/utils/GoogleMapSearch/styles.scss": {
      "input": "input_2BG",
      "_style": "/* stylelint-disable */\n/* stylelint-enable */\n/* stylelint-disable */\n/* stylelint-enable */\n.input_2BG {\n  font-size: 14px;\n  font-size: 0.875rem;\n  position: absolute;\n  top: auto !important;\n  bottom: 30px !important;\n  left: 80px !important;\n  box-sizing: border-box;\n  width: 350px;\n  height: 40px;\n  margin-top: 27px;\n  padding: 0 12px;\n  text-overflow: ellipsis;\n  border: 1px solid transparent;\n  border-radius: 1px;\n  outline: none;\n  box-shadow: 0 2px 6px rgba(0, 0, 0, 0.3); }\n"
    },
    "./common/components/forms/site/PhaseMainSite/styles.scss": {
      "footer": "footer_3yN",
      "google-map": "google-map_TLM",
      "googleMap": "google-map_TLM",
      "option-label": "option-label_3R-",
      "optionLabel": "option-label_3R-",
      "form-group": "form-group_2Qv",
      "formGroup": "form-group_2Qv",
      "_style": "/* stylelint-disable */\n/* stylelint-enable */\n/* stylelint-disable */\n/* stylelint-enable */\n.footer_3yN {\n  margin: 40px 0; }\n\n.google-map_TLM {\n  width: 100%;\n  height: 300px;\n  margin-bottom: 20px; }\n\n.option-label_3R- {\n  font-size: 15px;\n  font-size: 0.9375rem;\n  margin-bottom: 10px;\n  font-weight: 700;\n  text-align: right; }\n\n.form-group_2Qv {\n  margin-bottom: 0 !important; }\n"
    },
    "./common/components/forms/site/PhaseSubSite/styles.scss": {
      "google-map": "google-map_1oD",
      "googleMap": "google-map_1oD",
      "option-label": "option-label_2lb",
      "optionLabel": "option-label_2lb",
      "form-group": "form-group_3bG",
      "formGroup": "form-group_3bG",
      "subsite-div": "subsite-div_2ZB",
      "subsiteDiv": "subsite-div_2ZB",
      "subsite-div-active": "subsite-div-active_3xd",
      "subsiteDivActive": "subsite-div-active_3xd",
      "subsite-div-inactive": "subsite-div-inactive_1Ee",
      "subsiteDivInactive": "subsite-div-inactive_1Ee",
      "field-active": "field-active_eUz",
      "fieldActive": "field-active_eUz",
      "field-inactive": "field-inactive_2Fd",
      "fieldInactive": "field-inactive_2Fd",
      "title-div": "title-div_2Ek",
      "titleDiv": "title-div_2Ek",
      "title-div-title": "title-div-title_1XD",
      "titleDivTitle": "title-div-title_1XD",
      "btn-trash": "btn-trash_VMD",
      "btnTrash": "btn-trash_VMD",
      "footer": "footer_1AX",
      "btn-div": "btn-div_B0e",
      "btnDiv": "btn-div_B0e",
      "add-btn": "add-btn_2hX",
      "addBtn": "add-btn_2hX",
      "_style": "/* stylelint-disable */\n/* stylelint-enable */\n/* stylelint-disable */\n/* stylelint-enable */\n.google-map_1oD {\n  width: 100%;\n  height: 300px;\n  margin-bottom: 20px; }\n\n.option-label_2lb {\n  font-size: 15px;\n  font-size: 0.9375rem;\n  margin-bottom: 10px;\n  font-weight: 700;\n  text-align: right; }\n\n.form-group_3bG {\n  margin-bottom: 0 !important; }\n\n.subsite-div_2ZB, .subsite-div-active_3xd, .subsite-div-inactive_1Ee {\n  margin-bottom: 15px;\n  padding: 5px 0; }\n\n.subsite-div-inactive_1Ee {\n  margin-bottom: 0;\n  border-bottom: none; }\n\n.field-active_eUz {\n  display: block; }\n\n.field-inactive_2Fd {\n  display: none; }\n\n.title-div_2Ek {\n  display: -webkit-box;\n  display: -ms-flexbox;\n  display: flex;\n  -webkit-box-orient: horizontal;\n  -webkit-box-direction: normal;\n      -ms-flex-direction: row;\n          flex-direction: row;\n  -webkit-box-pack: justify;\n      -ms-flex-pack: justify;\n          justify-content: space-between;\n  margin-bottom: 10px;\n  padding: 5px 20px;\n  border-left: 5px #f78b6d solid;\n  background-color: #ffffff;\n  cursor: pointer; }\n  .title-div_2Ek:hover {\n    background-color: #f0f0f0; }\n\n.title-div-title_1XD {\n  display: -webkit-box;\n  display: -ms-flexbox;\n  display: flex;\n  -webkit-box-pack: center;\n      -ms-flex-pack: center;\n          justify-content: center;\n  -webkit-box-align: center;\n      -ms-flex-align: center;\n          align-items: center;\n  color: #f78b6d; }\n\n.btn-trash_VMD {\n  font-size: 18px !important;\n  font-size: 1.125rem !important;\n  width: 30px !important;\n  height: 30px !important;\n  color: #f78b6d;\n  background-color: transparent !important; }\n\n.footer_1AX {\n  margin: 15px 0; }\n\n.btn-div_B0e {\n  width: 100%;\n  height: 30px;\n  margin-top: 20px; }\n\n.add-btn_2hX {\n  font-size: 16px;\n  font-size: 1rem;\n  float: right;\n  color: #f78b6d;\n  border: 0;\n  background: transparent; }\n  .add-btn_2hX:focus {\n    outline: 0; }\n"
    },
    "./common/components/forms/site/PhaseOtherInfo/styles.scss": {
      "footer": "footer_20I",
      "option-label": "option-label_1kx",
      "optionLabel": "option-label_1kx",
      "title-div": "title-div_3CY",
      "titleDiv": "title-div_3CY",
      "title-div-title": "title-div-title_28V",
      "titleDivTitle": "title-div-title_28V",
      "btn-trash": "btn-trash_wg3",
      "btnTrash": "btn-trash_wg3",
      "add-btn": "add-btn_1_F",
      "addBtn": "add-btn_1_F",
      "_style": "/* stylelint-disable */\n/* stylelint-enable */\n/* stylelint-disable */\n/* stylelint-enable */\n.footer_20I {\n  margin: 60px 0 30px; }\n\n.option-label_1kx {\n  font-size: 15px;\n  font-size: 0.9375rem;\n  margin-bottom: 10px;\n  font-weight: 700; }\n\n.title-div_3CY {\n  display: -webkit-box;\n  display: -ms-flexbox;\n  display: flex;\n  -webkit-box-orient: horizontal;\n  -webkit-box-direction: normal;\n      -ms-flex-direction: row;\n          flex-direction: row;\n  -webkit-box-pack: justify;\n      -ms-flex-pack: justify;\n          justify-content: space-between;\n  margin-bottom: 10px;\n  padding: 5px 20px;\n  border-left: 5px #f78b6d solid;\n  background-color: #ffffff;\n  cursor: pointer; }\n\n.title-div-title_28V {\n  display: -webkit-box;\n  display: -ms-flexbox;\n  display: flex;\n  -webkit-box-pack: center;\n      -ms-flex-pack: center;\n          justify-content: center;\n  -webkit-box-align: center;\n      -ms-flex-align: center;\n          align-items: center;\n  color: #f78b6d; }\n\n.btn-trash_wg3 {\n  font-size: 18px !important;\n  font-size: 1.125rem !important;\n  width: 30px !important;\n  height: 30px !important;\n  color: #f78b6d;\n  background-color: transparent !important; }\n\n.add-btn_1_F {\n  font-size: 16px;\n  font-size: 1rem;\n  float: right;\n  color: #f78b6d;\n  border: 0;\n  background: transparent; }\n  .add-btn_1_F:focus {\n    outline: 0; }\n"
    },
    "./common/components/forms/site/PhaseDone/styles.scss": {
      "container": "container_HUd",
      "img-done": "img-done_2V8",
      "imgDone": "img-done_2V8",
      "comment": "comment_16q",
      "btn": "btn_1Sr",
      "_style": "/* stylelint-disable */\n/* stylelint-enable */\n/* stylelint-disable */\n/* stylelint-enable */\n.container_HUd {\n  display: -webkit-box;\n  display: -ms-flexbox;\n  display: flex;\n  -webkit-box-orient: vertical;\n  -webkit-box-direction: normal;\n      -ms-flex-direction: column;\n          flex-direction: column;\n  -webkit-box-align: center;\n      -ms-flex-align: center;\n          align-items: center;\n  padding: 20px; }\n\n.img-done_2V8 {\n  width: 150px;\n  height: 150px;\n  background: transparent url(/img/createsitepage/icon_finish.png) no-repeat center center;\n  background-size: contain;\n  margin: 0 auto 30px; }\n\n.comment_16q {\n  font-size: 16px;\n  font-size: 1rem;\n  margin-bottom: 30px; }\n\n.btn_1Sr {\n  width: auto;\n  padding: 8px 20px; }\n"
    },
    "./common/container/trip/CreateSitePage/styles.scss": {
      "none": "none_1fO",
      "_style": "/* stylelint-disable */\n/* stylelint-enable */\n/* stylelint-disable */\n/* stylelint-enable */\n.none_1fO {\n  display: none; }\n"
    },
    "./common/components/order/MenuItem/styles.scss": {
      "btn": "btn_1lZ",
      "container": "container_1bK",
      "info-div": "info-div_UAd",
      "infoDiv": "info-div_UAd",
      "name": "name_3y-",
      "custom-info": "custom-info_11O",
      "customInfo": "custom-info_11O",
      "info-label": "info-label_1L1",
      "infoLabel": "info-label_1L1",
      "label-icon": "label-icon_3ya",
      "labelIcon": "label-icon_3ya",
      "label": "label_hgu",
      "avatar-div": "avatar-div_3mr",
      "avatarDiv": "avatar-div_3mr",
      "avatar": "avatar_1f6",
      "phase-div": "phase-div_3ZO",
      "phaseDiv": "phase-div_3ZO",
      "phase": "phase_3O2",
      "phase-guide-confirm": "phase-guide-confirm_1yv",
      "phaseGuideConfirm": "phase-guide-confirm_1yv",
      "phase-deposit": "phase-deposit_2hd",
      "phaseDeposit": "phase-deposit_2hd",
      "phase-time-confirm": "phase-time-confirm_dIp",
      "phaseTimeConfirm": "phase-time-confirm_dIp",
      "phase-video-wait": "phase-video-wait_GeP",
      "phaseVideoWait": "phase-video-wait_GeP",
      "phase-balance": "phase-balance_2IG",
      "phaseBalance": "phase-balance_2IG",
      "phase-buy": "phase-buy_LT3",
      "phaseBuy": "phase-buy_LT3",
      "_style": "/* stylelint-disable */\n/* stylelint-enable */\n/* stylelint-disable */\n/* stylelint-enable */\n.btn_1lZ {\n  width: 100%;\n  height: 90px;\n  margin: 10px 0;\n  padding: 0;\n  text-align: left;\n  border: 0;\n  background-color: #ffffff;\n  box-shadow: 3px 3px 8px 0 #cccccc; }\n  .btn_1lZ:hover {\n    background-color: #f0f0f0; }\n\n.container_1bK {\n  display: -webkit-box;\n  display: -ms-flexbox;\n  display: flex;\n  -webkit-box-orient: horizontal;\n  -webkit-box-direction: normal;\n      -ms-flex-direction: row;\n          flex-direction: row;\n  height: 100%; }\n\n.info-div_UAd {\n  display: -webkit-box;\n  display: -ms-flexbox;\n  display: flex;\n  -webkit-box-orient: vertical;\n  -webkit-box-direction: normal;\n      -ms-flex-direction: column;\n          flex-direction: column;\n  -webkit-box-flex: 1;\n      -ms-flex: 1;\n          flex: 1;\n  height: 100%;\n  padding: 10px;\n  letter-spacing: 1px; }\n\n.name_3y- {\n  font-size: 18px;\n  font-size: 1.125rem;\n  display: -webkit-box;\n  display: -ms-flexbox;\n  display: flex;\n  -webkit-box-orient: horizontal;\n  -webkit-box-direction: normal;\n      -ms-flex-direction: row;\n          flex-direction: row;\n  -webkit-box-align: center;\n      -ms-flex-align: center;\n          align-items: center;\n  -webkit-box-flex: 1;\n      -ms-flex: 1;\n          flex: 1;\n  color: #000000; }\n\n.custom-info_11O {\n  display: -webkit-box;\n  display: -ms-flexbox;\n  display: flex;\n  -webkit-box-orient: horizontal;\n  -webkit-box-direction: normal;\n      -ms-flex-direction: row;\n          flex-direction: row;\n  -webkit-box-align: center;\n      -ms-flex-align: center;\n          align-items: center;\n  -webkit-box-flex: 1;\n      -ms-flex: 1;\n          flex: 1;\n  color: #000000; }\n\n.info-label_1L1 {\n  display: -webkit-box;\n  display: -ms-flexbox;\n  display: flex;\n  -webkit-box-orient: horizontal;\n  -webkit-box-direction: normal;\n      -ms-flex-direction: row;\n          flex-direction: row;\n  -webkit-box-pack: end;\n      -ms-flex-pack: end;\n          justify-content: flex-end;\n  margin-right: 20px; }\n\n.label-icon_3ya {\n  font-size: 16px;\n  font-size: 1rem;\n  margin-right: 5px;\n  color: #f78b6d; }\n\n.label_hgu {\n  font-size: 15px;\n  font-size: 0.9375rem; }\n\n.avatar-div_3mr {\n  display: -webkit-box;\n  display: -ms-flexbox;\n  display: flex;\n  -webkit-box-pack: center;\n      -ms-flex-pack: center;\n          justify-content: center;\n  -webkit-box-align: center;\n      -ms-flex-align: center;\n          align-items: center;\n  width: 90px;\n  height: 100%; }\n\n.avatar_1f6 {\n  width: 60px;\n  height: 60px;\n  background: transparent url(/img/default-avatar.png) no-repeat center center;\n  background-size: contain;\n  border-radius: 30px; }\n\n.phase-div_3ZO {\n  position: relative;\n  width: 110px;\n  height: 100%; }\n\n.phase_3O2, .phase-guide-confirm_1yv, .phase-deposit_2hd, .phase-time-confirm_dIp, .phase-video-wait_GeP, .phase-balance_2IG, .phase-buy_LT3 {\n  font-size: 14px;\n  font-size: 0.875rem;\n  position: absolute;\n  top: 15px;\n  right: 0;\n  width: 100%;\n  padding: 8px;\n  color: #f0f0f0;\n  letter-spacing: 2px; }\n\n.phase-guide-confirm_1yv {\n  background-color: #fd9f2c; }\n\n.phase-deposit_2hd {\n  background-color: #f53011; }\n\n.phase-time-confirm_dIp {\n  background-color: #fd9f2c; }\n\n.phase-video-wait_GeP {\n  background-color: #9acd32; }\n\n.phase-balance_2IG {\n  background-color: #f53011; }\n\n.phase-buy_LT3 {\n  background-color: #008000; }\n"
    },
    "./common/components/order/PhaseOutline/styles.scss": {
      "block": "block_3aW",
      "title": "title_2L3",
      "container": "container_1cG",
      "comment": "comment_TVI",
      "waiting-img": "waiting-img_2bu",
      "waitingImg": "waiting-img_2bu",
      "rank": "rank_1l0",
      "info": "info_uGM",
      "guide-info1": "guide-info1_1AK",
      "guideInfo1": "guide-info1_1AK",
      "guide-info1-left": "guide-info1-left_291",
      "guideInfo1Left": "guide-info1-left_291",
      "guide-info1-right": "guide-info1-right_2V-",
      "guideInfo1Right": "guide-info1-right_2V-",
      "guide-name": "guide-name_2XT",
      "guideName": "guide-name_2XT",
      "profession": "profession_2oF",
      "avatar": "avatar_2Ow",
      "guide-info2": "guide-info2_11j",
      "guideInfo2": "guide-info2_11j",
      "small-info-title": "small-info-title_39K",
      "smallInfoTitle": "small-info-title_39K",
      "small-info-content": "small-info-content_Wzx",
      "smallInfoContent": "small-info-content_Wzx",
      "self-intro": "self-intro_3Zs",
      "selfIntro": "self-intro_3Zs",
      "option": "option_vgo",
      "option-label": "option-label_1xP",
      "optionLabel": "option-label_1xP",
      "option-label1": "option-label1_3uu",
      "optionLabel1": "option-label1_3uu",
      "option-label2": "option-label2_Da7",
      "optionLabel2": "option-label2_Da7",
      "option-value": "option-value_2uq",
      "optionValue": "option-value_2uq",
      "option-value-element": "option-value-element__2a",
      "optionValueElement": "option-value-element__2a",
      "element": "element_UrL",
      "blackline": "blackline_3-E",
      "footer": "footer_2jD",
      "footer-btn": "footer-btn_3ba",
      "footerBtn": "footer-btn_3ba",
      "_style": "/* stylelint-disable */\n/* stylelint-enable */\n/* stylelint-disable */\n/* stylelint-enable */\n.block_3aW {\n  padding: 15px;\n  text-align: center; }\n\n.title_2L3 {\n  font-size: 22px;\n  font-size: 1.375rem;\n  color: #f78b6d; }\n\n.container_1cG {\n  padding: 0 15px;\n  text-align: center; }\n\n.comment_TVI {\n  font-size: 18px;\n  font-size: 1.125rem;\n  line-height: 30px; }\n\n.waiting-img_2bu {\n  width: 120px;\n  height: 120px;\n  background: transparent url(/img/custompage/waiting.png) no-repeat center center;\n  background-size: contain;\n  margin: 0 auto 30px;\n  border-radius: 60px; }\n\n.rank_1l0 {\n  font-size: 16px;\n  font-size: 1rem;\n  position: absolute;\n  top: 15px;\n  right: 15px; }\n\n.info_uGM {\n  display: -webkit-box;\n  display: -ms-flexbox;\n  display: flex;\n  -webkit-box-orient: vertical;\n  -webkit-box-direction: normal;\n      -ms-flex-direction: column;\n          flex-direction: column;\n  position: relative;\n  width: 100%;\n  margin-top: 20px;\n  padding: 20px;\n  border: 0;\n  background-color: #ffffff;\n  box-shadow: 3px 3px 8px 0 #cccccc; }\n\n.guide-info1_1AK {\n  display: -webkit-box;\n  display: -ms-flexbox;\n  display: flex;\n  -webkit-box-orient: horizontal;\n  -webkit-box-direction: normal;\n      -ms-flex-direction: row;\n          flex-direction: row;\n  width: 100%; }\n\n.guide-info1-left_291 {\n  display: -webkit-box;\n  display: -ms-flexbox;\n  display: flex;\n  -webkit-box-orient: vertical;\n  -webkit-box-direction: normal;\n      -ms-flex-direction: column;\n          flex-direction: column;\n  -webkit-box-align: end;\n      -ms-flex-align: end;\n          align-items: flex-end;\n  -webkit-box-flex: 1;\n      -ms-flex: 1;\n          flex: 1;\n  margin: 0 10px; }\n\n.guide-info1-right_2V- {\n  display: -webkit-box;\n  display: -ms-flexbox;\n  display: flex;\n  -webkit-box-orient: horizontal;\n  -webkit-box-direction: normal;\n      -ms-flex-direction: row;\n          flex-direction: row;\n  -webkit-box-pack: start;\n      -ms-flex-pack: start;\n          justify-content: flex-start;\n  -webkit-box-flex: 1;\n      -ms-flex: 1;\n          flex: 1;\n  -webkit-box-align: center;\n      -ms-flex-align: center;\n          align-items: center;\n  margin: 0 10px;\n  text-align: left; }\n\n.guide-name_2XT {\n  font-size: 24px;\n  font-size: 1.5rem;\n  font-weight: bold;\n  line-height: 30px; }\n\n.profession_2oF {\n  font-size: 14px;\n  font-size: 0.875rem;\n  line-height: 20px; }\n\n.avatar_2Ow {\n  width: 60px;\n  height: 60px;\n  background: transparent url(/img/default-avatar.png) no-repeat center center;\n  background-size: contain;\n  margin: auto 0;\n  border-radius: 30px; }\n\n.guide-info2_11j {\n  margin: 30px 0; }\n\n.small-info-title_39K {\n  font-size: 18px;\n  font-size: 1.125rem;\n  font-weight: 900;\n  line-height: 25px; }\n\n.small-info-content_Wzx {\n  font-size: 14px;\n  font-size: 0.875rem;\n  line-height: 25px; }\n\n.self-intro_3Zs {\n  padding: 0 10px 20px;\n  text-align: left; }\n\n.option_vgo {\n  display: -webkit-box;\n  display: -ms-flexbox;\n  display: flex;\n  -webkit-box-orient: horizontal;\n  -webkit-box-direction: normal;\n      -ms-flex-direction: row;\n          flex-direction: row;\n  -webkit-box-pack: start;\n      -ms-flex-pack: start;\n          justify-content: flex-start;\n  margin: 10px 0;\n  text-align: left; }\n\n.option-label_1xP, .option-label1_3uu, .option-label2_Da7 {\n  color: #f78b6d; }\n\n.option-label1_3uu {\n  width: 90px; }\n\n.option-label2_Da7 {\n  width: 150px; }\n\n.option-value_2uq, .option-value-element__2a {\n  display: -webkit-box;\n  display: -ms-flexbox;\n  display: flex;\n  -webkit-box-orient: horizontal;\n  -webkit-box-direction: normal;\n      -ms-flex-direction: row;\n          flex-direction: row;\n  -ms-flex-wrap: wrap;\n      flex-wrap: wrap;\n  -webkit-box-flex: 1;\n      -ms-flex: 1;\n          flex: 1; }\n\n.option-value-element__2a {\n  position: relative;\n  top: -3px; }\n\n.element_UrL {\n  font-size: 14px;\n  font-size: 0.875rem;\n  margin-right: 5px;\n  margin-bottom: 5px;\n  padding: 0 4px;\n  line-height: 22px;\n  border: solid #000000 1px;\n  border-radius: 3px; }\n\n.blackline_3-E {\n  width: 100%;\n  height: 1px;\n  margin: 5px 0 10px;\n  background-color: #666666; }\n\n.footer_2jD {\n  display: -webkit-box;\n  display: -ms-flexbox;\n  display: flex;\n  -webkit-box-pack: center;\n      -ms-flex-pack: center;\n          justify-content: center;\n  -webkit-box-align: center;\n      -ms-flex-align: center;\n          align-items: center;\n  margin: 30px 0; }\n\n.footer-btn_3ba {\n  margin: 0 15px; }\n"
    },
    "./common/components/utils/IconRectBtn/styles.scss": {
      "btn": "btn_17J",
      "icon": "icon_1TM",
      "btnText": "btnText_bgr",
      "_style": "/* stylelint-disable */\n/* stylelint-enable */\n/* stylelint-disable */\n/* stylelint-enable */\n.btn_17J {\n  font-size: 14px;\n  font-size: 0.875rem;\n  display: -webkit-box;\n  display: -ms-flexbox;\n  display: flex;\n  -webkit-box-orient: horizontal;\n  -webkit-box-direction: normal;\n      -ms-flex-direction: row;\n          flex-direction: row;\n  -webkit-box-pack: justify;\n      -ms-flex-pack: justify;\n          justify-content: space-between;\n  width: 110px;\n  height: 34px;\n  padding: 5px 10px 5px 12px;\n  color: #ffffff;\n  letter-spacing: 2px;\n  border: 0;\n  border-radius: 3px;\n  background-color: #f78b6d; }\n\n.icon_1TM {\n  background-color: transparent; }\n\n.btnText_bgr {\n  -webkit-box-flex: 1;\n      -ms-flex: 1;\n          flex: 1; }\n"
    },
    "./common/components/order/PhaseDeposit/styles.scss": {
      "container": "container_3Dy",
      "pic": "pic_1cQ",
      "pic-unfinish": "pic-unfinish_lcc",
      "picUnfinish": "pic-unfinish_lcc",
      "pic-finish": "pic-finish_u5Q",
      "picFinish": "pic-finish_u5Q",
      "comment": "comment_3NP",
      "comment-finish": "comment-finish_2Nu",
      "commentFinish": "comment-finish_2Nu",
      "comment-unfinish": "comment-unfinish_2yz",
      "commentUnfinish": "comment-unfinish_2yz",
      "_style": "/* stylelint-disable */\n/* stylelint-enable */\n/* stylelint-disable */\n/* stylelint-enable */\n.container_3Dy {\n  display: -webkit-box;\n  display: -ms-flexbox;\n  display: flex;\n  -webkit-box-orient: vertical;\n  -webkit-box-direction: normal;\n      -ms-flex-direction: column;\n          flex-direction: column;\n  -webkit-box-align: center;\n      -ms-flex-align: center;\n          align-items: center; }\n\n.pic_1cQ, .pic-unfinish_lcc, .pic-finish_u5Q {\n  height: 100px; }\n\n.pic-unfinish_lcc {\n  width: 120px;\n  height: 120px;\n  background: transparent url(/img/custompage/moneytransfer.png) no-repeat center center;\n  background-size: contain; }\n\n.pic-finish_u5Q {\n  width: 120px;\n  height: 120px;\n  background: transparent url(/img/createsitepage/icon_finish.png) no-repeat center center;\n  background-size: contain; }\n\n.comment_3NP, .comment-finish_2Nu, .comment-unfinish_2yz {\n  width: 70%;\n  margin-top: 30px;\n  line-height: 25px;\n  text-align: center; }\n"
    },
    "./common/components/order/PhaseCustomize/styles.scss": {
      "container": "container_18Q",
      "option": "option_1Hg",
      "pic": "pic_2v1",
      "pic-create": "pic-create_1S2",
      "picCreate": "pic-create_1S2",
      "pic-choose": "pic-choose_Fdb",
      "picChoose": "pic-choose_Fdb",
      "comment": "comment_1uT",
      "_style": "/* stylelint-disable */\n/* stylelint-enable */\n/* stylelint-disable */\n/* stylelint-enable */\n.container_18Q {\n  display: -webkit-box;\n  display: -ms-flexbox;\n  display: flex;\n  -webkit-box-orient: horizontal;\n  -webkit-box-direction: normal;\n      -ms-flex-direction: row;\n          flex-direction: row;\n  -webkit-box-align: center;\n      -ms-flex-align: center;\n          align-items: center;\n  width: 80%;\n  margin: 0 auto; }\n\n.option_1Hg {\n  display: -webkit-box;\n  display: -ms-flexbox;\n  display: flex;\n  -webkit-box-orient: vertical;\n  -webkit-box-direction: normal;\n      -ms-flex-direction: column;\n          flex-direction: column;\n  -webkit-box-align: center;\n      -ms-flex-align: center;\n          align-items: center;\n  -webkit-box-flex: 1;\n      -ms-flex: 1;\n          flex: 1; }\n\n.pic_2v1, .pic-create_1S2, .pic-choose_Fdb {\n  height: 100px; }\n\n.pic-create_1S2 {\n  width: 80px;\n  height: 80px;\n  background: transparent url(/img/orderpage/create.png) no-repeat center center;\n  background-size: contain; }\n\n.pic-choose_Fdb {\n  width: 80px;\n  height: 80px;\n  background: transparent url(/img/orderpage/choose.png) no-repeat center center;\n  background-size: contain; }\n\n.comment_1uT {\n  display: -webkit-box;\n  display: -ms-flexbox;\n  display: flex;\n  -webkit-box-pack: center;\n      -ms-flex-pack: center;\n          justify-content: center;\n  -webkit-box-align: center;\n      -ms-flex-align: center;\n          align-items: center;\n  height: 70px;\n  line-height: 20px;\n  text-align: center; }\n"
    },
    "./common/components/order/PhaseBalance/styles.scss": {
      "container": "container_1XX",
      "pic": "pic_2Qr",
      "pic-unfinish": "pic-unfinish_2uq",
      "picUnfinish": "pic-unfinish_2uq",
      "pic-finish": "pic-finish_2Uo",
      "picFinish": "pic-finish_2Uo",
      "comment": "comment_ezo",
      "comment-finish": "comment-finish_25Y",
      "commentFinish": "comment-finish_25Y",
      "comment-unfinish": "comment-unfinish_2WQ",
      "commentUnfinish": "comment-unfinish_2WQ",
      "_style": "/* stylelint-disable */\n/* stylelint-enable */\n/* stylelint-disable */\n/* stylelint-enable */\n.container_1XX {\n  display: -webkit-box;\n  display: -ms-flexbox;\n  display: flex;\n  -webkit-box-orient: vertical;\n  -webkit-box-direction: normal;\n      -ms-flex-direction: column;\n          flex-direction: column;\n  -webkit-box-align: center;\n      -ms-flex-align: center;\n          align-items: center; }\n\n.pic_2Qr, .pic-unfinish_2uq, .pic-finish_2Uo {\n  height: 100px; }\n\n.pic-unfinish_2uq {\n  width: 120px;\n  height: 120px;\n  background: transparent url(/img/custompage/moneytransfer.png) no-repeat center center;\n  background-size: contain; }\n\n.pic-finish_2Uo {\n  width: 120px;\n  height: 120px;\n  background: transparent url(/img/createsitepage/icon_finish.png) no-repeat center center;\n  background-size: contain; }\n\n.comment_ezo, .comment-finish_25Y, .comment-unfinish_2WQ {\n  width: 70%;\n  margin-top: 30px;\n  line-height: 25px;\n  text-align: center; }\n"
    },
    "./common/components/order/PhaseVideo/styles.scss": {
      "container": "container_p0s",
      "pic": "pic_20n",
      "pic-unfinish": "pic-unfinish_1l5",
      "picUnfinish": "pic-unfinish_1l5",
      "pic-finish": "pic-finish_35k",
      "picFinish": "pic-finish_35k",
      "comment": "comment_2pw",
      "comment-finish": "comment-finish_37S",
      "commentFinish": "comment-finish_37S",
      "comment-unfinish": "comment-unfinish_2hr",
      "commentUnfinish": "comment-unfinish_2hr",
      "title": "title_6VR",
      "item": "item_1IE",
      "item-active": "item-active_3PO",
      "itemActive": "item-active_3PO",
      "item-inactive": "item-inactive_uZH",
      "itemInactive": "item-inactive_uZH",
      "item-date": "item-date_8FK",
      "itemDate": "item-date_8FK",
      "footer": "footer_bR5",
      "footer-btn": "footer-btn_3ZT",
      "footerBtn": "footer-btn_3ZT",
      "_style": "/* stylelint-disable */\n/* stylelint-enable */\n/* stylelint-disable */\n/* stylelint-enable */\n.container_p0s {\n  display: -webkit-box;\n  display: -ms-flexbox;\n  display: flex;\n  -webkit-box-orient: vertical;\n  -webkit-box-direction: normal;\n      -ms-flex-direction: column;\n          flex-direction: column;\n  -webkit-box-align: center;\n      -ms-flex-align: center;\n          align-items: center;\n  width: 100%;\n  padding: 20px 60px;\n  border: 0;\n  background-color: #ffffff;\n  box-shadow: 3px 3px 8px 0 #cccccc; }\n\n.pic_20n, .pic-unfinish_1l5, .pic-finish_35k {\n  height: 100px; }\n\n.pic-unfinish_1l5 {\n  width: 120px;\n  height: 120px;\n  background: transparent url(/img/custompage/moneytransfer.png) no-repeat center center;\n  background-size: contain; }\n\n.pic-finish_35k {\n  width: 120px;\n  height: 120px;\n  background: transparent url(/img/createsitepage/icon_finish.png) no-repeat center center;\n  background-size: contain; }\n\n.comment_2pw, .comment-finish_37S, .comment-unfinish_2hr {\n  width: 70%;\n  margin-top: 30px;\n  line-height: 25px;\n  text-align: center; }\n\n.title_6VR {\n  margin-bottom: 20px; }\n\n.item_1IE, .item-active_3PO, .item-inactive_uZH {\n  display: -webkit-box;\n  display: -ms-flexbox;\n  display: flex;\n  -webkit-box-orient: horizontal;\n  -webkit-box-direction: normal;\n      -ms-flex-direction: row;\n          flex-direction: row;\n  -ms-flex-pack: distribute;\n      justify-content: space-around;\n  width: 100%;\n  padding: 10px 40px;\n  border: 1px none #666666;\n  border-bottom-style: solid;\n  background-color: transparent; }\n  .item_1IE:focus, .item-active_3PO:focus, .item-inactive_uZH:focus {\n    outline: 0; }\n\n.item-active_3PO {\n  color: #ffffff;\n  background-color: #f99e85; }\n\n.item-date_8FK {\n  -webkit-box-flex: 1;\n      -ms-flex: 1;\n          flex: 1;\n  text-align: left; }\n\n.footer_bR5 {\n  display: -webkit-box;\n  display: -ms-flexbox;\n  display: flex;\n  -webkit-box-pack: center;\n      -ms-flex-pack: center;\n          justify-content: center;\n  -webkit-box-align: center;\n      -ms-flex-align: center;\n          align-items: center;\n  margin: 30px 0 15px; }\n\n.footer-btn_3ZT {\n  margin: 0 15px; }\n"
    },
    "./common/container/order/MyOrderPhasePage/styles.scss": {
      "btn-confirm": "btn-confirm_3Xl",
      "btnConfirm": "btn-confirm_3Xl",
      "main-panel": "main-panel_2zI",
      "mainPanel": "main-panel_2zI",
      "finish-panel": "finish-panel_YeO",
      "finishPanel": "finish-panel_YeO",
      "double-title-content": "double-title-content_3Sf",
      "doubleTitleContent": "double-title-content_3Sf",
      "panel-title": "panel-title_1Im",
      "panelTitle": "panel-title_1Im",
      "_style": "/* stylelint-disable */\n/* stylelint-enable */\n/* stylelint-disable */\n/* stylelint-enable */\n.btn-confirm_3Xl {\n  margin: 45px auto 5px; }\n\n.main-panel_2zI {\n  padding: 20px 5px; }\n\n.finish-panel_YeO {\n  font-size: 20px;\n  font-size: 1.25rem;\n  padding: 20px 5px;\n  background-color: transparent; }\n\n.double-title-content_3Sf {\n  margin: 0 !important;\n  padding: 0 15px !important; }\n\n.panel-title_1Im {\n  color: #f78b6d !important; }\n"
    },
    "./common/components/custom/MenuItem/styles.scss": {
      "btn": "btn_1_s",
      "container": "container_nr7",
      "info-div": "info-div_3SR",
      "infoDiv": "info-div_3SR",
      "title": "title_1na",
      "guide-info": "guide-info_QeP",
      "guideInfo": "guide-info_QeP",
      "guide-name": "guide-name_3u3",
      "guideName": "guide-name_3u3",
      "avatar": "avatar_3Km",
      "day-info": "day-info_e2o",
      "dayInfo": "day-info_e2o",
      "phase-div": "phase-div_1eF",
      "phaseDiv": "phase-div_1eF",
      "phase": "phase_3Ly",
      "phase-guide-confirm": "phase-guide-confirm_37O",
      "phaseGuideConfirm": "phase-guide-confirm_37O",
      "phase-deposit": "phase-deposit_3fo",
      "phaseDeposit": "phase-deposit_3fo",
      "phase-time-confirm": "phase-time-confirm_1jg",
      "phaseTimeConfirm": "phase-time-confirm_1jg",
      "phase-video-wait": "phase-video-wait_1vO",
      "phaseVideoWait": "phase-video-wait_1vO",
      "phase-balance": "phase-balance_1Jf",
      "phaseBalance": "phase-balance_1Jf",
      "phase-buy": "phase-buy_3_f",
      "phaseBuy": "phase-buy_3_f",
      "_style": "/* stylelint-disable */\n/* stylelint-enable */\n/* stylelint-disable */\n/* stylelint-enable */\n.btn_1_s {\n  width: 100%;\n  height: 90px;\n  margin: 10px 0;\n  padding: 0;\n  text-align: left;\n  border: 0;\n  background-color: #ffffff;\n  box-shadow: 3px 3px 8px 0 #cccccc; }\n  .btn_1_s:hover {\n    background-color: #f0f0f0; }\n\n.container_nr7 {\n  display: -webkit-box;\n  display: -ms-flexbox;\n  display: flex;\n  -webkit-box-orient: horizontal;\n  -webkit-box-direction: normal;\n      -ms-flex-direction: row;\n          flex-direction: row;\n  height: 100%; }\n\n.info-div_3SR {\n  display: -webkit-box;\n  display: -ms-flexbox;\n  display: flex;\n  -webkit-box-orient: vertical;\n  -webkit-box-direction: normal;\n      -ms-flex-direction: column;\n          flex-direction: column;\n  -webkit-box-flex: 1;\n      -ms-flex: 1;\n          flex: 1;\n  height: 100%;\n  padding: 10px 20px;\n  letter-spacing: 1px; }\n\n.title_1na {\n  font-size: 18px;\n  font-size: 1.125rem;\n  display: -webkit-box;\n  display: -ms-flexbox;\n  display: flex;\n  -webkit-box-orient: horizontal;\n  -webkit-box-direction: normal;\n      -ms-flex-direction: row;\n          flex-direction: row;\n  -webkit-box-align: center;\n      -ms-flex-align: center;\n          align-items: center;\n  -webkit-box-flex: 1;\n      -ms-flex: 1;\n          flex: 1;\n  color: #000000; }\n\n.guide-info_QeP {\n  display: -webkit-box;\n  display: -ms-flexbox;\n  display: flex;\n  -webkit-box-orient: horizontal;\n  -webkit-box-direction: normal;\n      -ms-flex-direction: row;\n          flex-direction: row;\n  -webkit-box-align: center;\n      -ms-flex-align: center;\n          align-items: center;\n  -webkit-box-flex: 1;\n      -ms-flex: 1;\n          flex: 1;\n  color: #000000; }\n\n.guide-name_3u3 {\n  font-size: 16px;\n  font-size: 1rem;\n  margin-left: 15px; }\n\n.avatar_3Km {\n  width: 32px;\n  height: 32px;\n  background: transparent url(/img/default-avatar.png) no-repeat center center;\n  background-size: contain;\n  border-radius: 16px; }\n\n.day-info_e2o {\n  font-size: 12px;\n  font-size: 0.75rem;\n  margin-left: 15px;\n  padding: 2px;\n  border: 1px solid grey; }\n\n.phase-div_1eF {\n  position: relative;\n  width: 110px;\n  height: 100%; }\n\n.phase_3Ly, .phase-guide-confirm_37O, .phase-deposit_3fo, .phase-time-confirm_1jg, .phase-video-wait_1vO, .phase-balance_1Jf, .phase-buy_3_f {\n  font-size: 14px;\n  font-size: 0.875rem;\n  position: absolute;\n  top: 15px;\n  right: 0;\n  width: 100%;\n  padding: 8px;\n  color: #f0f0f0;\n  letter-spacing: 2px; }\n\n.phase-guide-confirm_37O {\n  background-color: #fd9f2c; }\n\n.phase-deposit_3fo {\n  background-color: #f53011; }\n\n.phase-time-confirm_1jg {\n  background-color: #fd9f2c; }\n\n.phase-video-wait_1vO {\n  background-color: #9acd32; }\n\n.phase-balance_1Jf {\n  background-color: #f53011; }\n\n.phase-buy_3_f {\n  background-color: #008000; }\n"
    },
    "./common/components/custom/PhaseChooseGuide/styles.scss": {
      "container": "container_2sp",
      "info-div": "info-div_2w7",
      "infoDiv": "info-div_2w7",
      "guide-name": "guide-name_3sl",
      "guideName": "guide-name_3sl",
      "profession": "profession_3af",
      "star-div": "star-div_1Od",
      "starDiv": "star-div_1Od",
      "star-text": "star-text_1tC",
      "starText": "star-text_1tC",
      "avatar": "avatar_25v",
      "other-div": "other-div_16A",
      "otherDiv": "other-div_16A",
      "rank": "rank_Zjm",
      "detail": "detail_qax",
      "_style": "/* stylelint-disable */\n/* stylelint-enable */\n/* stylelint-disable */\n/* stylelint-enable */\n.container_2sp {\n  display: -webkit-box;\n  display: -ms-flexbox;\n  display: flex;\n  -webkit-box-orient: horizontal;\n  -webkit-box-direction: normal;\n      -ms-flex-direction: row;\n          flex-direction: row;\n  width: 100%;\n  height: 100px;\n  margin: 10px 0;\n  padding: 15px 20px;\n  text-align: left;\n  border: 0;\n  background-color: #ffffff;\n  box-shadow: 3px 3px 8px 0 #cccccc;\n  cursor: -webkit-grab;\n  -webkit-user-select: none;\n     -moz-user-select: none;\n      -ms-user-select: none;\n          user-select: none; }\n  .container_2sp:hover {\n    background-color: #f0f0f0; }\n\n.info-div_2w7 {\n  display: -webkit-box;\n  display: -ms-flexbox;\n  display: flex;\n  -webkit-box-orient: vertical;\n  -webkit-box-direction: normal;\n      -ms-flex-direction: column;\n          flex-direction: column;\n  -webkit-box-flex: 1;\n      -ms-flex: 1;\n          flex: 1;\n  height: 100%;\n  padding: 0 20px;\n  letter-spacing: 1px; }\n\n.guide-name_3sl {\n  font-size: 20px;\n  font-size: 1.25rem;\n  display: -webkit-box;\n  display: -ms-flexbox;\n  display: flex;\n  -webkit-box-orient: horizontal;\n  -webkit-box-direction: normal;\n      -ms-flex-direction: row;\n          flex-direction: row;\n  -webkit-box-pack: end;\n      -ms-flex-pack: end;\n          justify-content: flex-end;\n  -webkit-box-flex: 1;\n      -ms-flex: 1;\n          flex: 1;\n  color: #000000; }\n\n.profession_3af {\n  font-size: 14px;\n  font-size: 0.875rem;\n  margin-left: 10px;\n  padding: 2px; }\n\n.star-div_1Od {\n  display: -webkit-box;\n  display: -ms-flexbox;\n  display: flex;\n  -webkit-box-orient: horizontal;\n  -webkit-box-direction: normal;\n      -ms-flex-direction: row;\n          flex-direction: row;\n  -webkit-box-pack: end;\n      -ms-flex-pack: end;\n          justify-content: flex-end;\n  -webkit-box-flex: 1;\n      -ms-flex: 1;\n          flex: 1;\n  padding-bottom: 5px;\n  color: #777777; }\n\n.star-text_1tC {\n  font-size: 14px;\n  font-size: 0.875rem;\n  position: relative;\n  top: -1px;\n  margin-right: 5px; }\n\n.avatar_25v {\n  width: 60px;\n  height: 60px;\n  background: transparent url(/img/default-avatar.png) no-repeat center center;\n  background-size: contain;\n  margin: auto 0;\n  border-radius: 30px; }\n\n.other-div_16A {\n  display: -webkit-box;\n  display: -ms-flexbox;\n  display: flex;\n  -webkit-box-orient: vertical;\n  -webkit-box-direction: normal;\n      -ms-flex-direction: column;\n          flex-direction: column;\n  position: relative;\n  -webkit-box-pack: justify;\n      -ms-flex-pack: justify;\n          justify-content: space-between;\n  height: 100%; }\n\n.rank_Zjm {\n  font-size: 16px;\n  font-size: 1rem;\n  font-weight: 900;\n  color: black;\n  text-align: right; }\n\n.detail_qax {\n  font-size: 14px;\n  font-size: 0.875rem;\n  display: -webkit-box;\n  display: -ms-flexbox;\n  display: flex;\n  -webkit-box-orient: horizontal;\n  -webkit-box-direction: normal;\n      -ms-flex-direction: row;\n          flex-direction: row;\n  -webkit-box-pack: justify;\n      -ms-flex-pack: justify;\n          justify-content: space-between;\n  width: 110px;\n  height: 34px;\n  padding: 5px 10px 5px 12px;\n  color: #ffffff;\n  letter-spacing: 2px;\n  border: 0;\n  border-radius: 3px;\n  background-color: #f78b6d; }\n"
    },
    "./common/components/utils/StarList/styles.scss": {
      "star-list": "star-list_1uF",
      "starList": "star-list_1uF",
      "star": "star_3n_",
      "_style": "/* stylelint-disable */\n/* stylelint-enable */\n/* stylelint-disable */\n/* stylelint-enable */\n.star-list_1uF {\n  display: -webkit-box;\n  display: -ms-flexbox;\n  display: flex;\n  -webkit-box-orient: horizontal;\n  -webkit-box-direction: normal;\n      -ms-flex-direction: row;\n          flex-direction: row; }\n\n.star_3n_ {\n  width: 16px;\n  height: 16px;\n  margin: 0 2px; }\n"
    },
    "./common/components/custom/PhaseGuideConfirm/styles.scss": {
      "container": "container_FYC",
      "comment": "comment_1uk",
      "waiting-img": "waiting-img_kHe",
      "waitingImg": "waiting-img_kHe",
      "rank": "rank_1lW",
      "guide-info": "guide-info_10Z",
      "guideInfo": "guide-info_10Z",
      "guide-info1": "guide-info1_1o8",
      "guideInfo1": "guide-info1_1o8",
      "guide-info1-left": "guide-info1-left_8kr",
      "guideInfo1Left": "guide-info1-left_8kr",
      "guide-info1-right": "guide-info1-right_NTW",
      "guideInfo1Right": "guide-info1-right_NTW",
      "guide-name": "guide-name_C4n",
      "guideName": "guide-name_C4n",
      "profession": "profession_1jf",
      "avatar": "avatar_3zs",
      "guide-info2": "guide-info2_3dt",
      "guideInfo2": "guide-info2_3dt",
      "small-info-title": "small-info-title_c49",
      "smallInfoTitle": "small-info-title_c49",
      "small-info-content": "small-info-content_1xA",
      "smallInfoContent": "small-info-content_1xA",
      "self-intro": "self-intro_3CW",
      "selfIntro": "self-intro_3CW",
      "_style": "/* stylelint-disable */\n/* stylelint-enable */\n/* stylelint-disable */\n/* stylelint-enable */\n.container_FYC {\n  padding: 0 15px;\n  text-align: center; }\n\n.comment_1uk {\n  font-size: 18px;\n  font-size: 1.125rem;\n  line-height: 30px; }\n\n.waiting-img_kHe {\n  width: 120px;\n  height: 120px;\n  background: transparent url(/img/custompage/waiting.png) no-repeat center center;\n  background-size: contain;\n  margin: 0 auto 30px;\n  border-radius: 60px; }\n\n.rank_1lW {\n  font-size: 16px;\n  font-size: 1rem;\n  position: absolute;\n  top: 15px;\n  right: 15px; }\n\n.guide-info_10Z {\n  display: -webkit-box;\n  display: -ms-flexbox;\n  display: flex;\n  -webkit-box-orient: vertical;\n  -webkit-box-direction: normal;\n      -ms-flex-direction: column;\n          flex-direction: column;\n  position: relative;\n  width: 100%;\n  margin-top: 20px;\n  padding: 20px;\n  border: 0;\n  background-color: #ffffff;\n  box-shadow: 3px 3px 8px 0 #cccccc; }\n\n.guide-info1_1o8 {\n  display: -webkit-box;\n  display: -ms-flexbox;\n  display: flex;\n  -webkit-box-orient: horizontal;\n  -webkit-box-direction: normal;\n      -ms-flex-direction: row;\n          flex-direction: row;\n  width: 100%; }\n\n.guide-info1-left_8kr {\n  display: -webkit-box;\n  display: -ms-flexbox;\n  display: flex;\n  -webkit-box-orient: vertical;\n  -webkit-box-direction: normal;\n      -ms-flex-direction: column;\n          flex-direction: column;\n  -webkit-box-align: end;\n      -ms-flex-align: end;\n          align-items: flex-end;\n  -webkit-box-flex: 1;\n      -ms-flex: 1;\n          flex: 1;\n  margin: 0 10px; }\n\n.guide-info1-right_NTW {\n  display: -webkit-box;\n  display: -ms-flexbox;\n  display: flex;\n  -webkit-box-orient: horizontal;\n  -webkit-box-direction: normal;\n      -ms-flex-direction: row;\n          flex-direction: row;\n  -webkit-box-pack: start;\n      -ms-flex-pack: start;\n          justify-content: flex-start;\n  -webkit-box-flex: 1;\n      -ms-flex: 1;\n          flex: 1;\n  -webkit-box-align: center;\n      -ms-flex-align: center;\n          align-items: center;\n  margin: 0 10px;\n  text-align: left; }\n\n.guide-name_C4n {\n  font-size: 24px;\n  font-size: 1.5rem;\n  font-weight: bold;\n  line-height: 30px; }\n\n.profession_1jf {\n  font-size: 14px;\n  font-size: 0.875rem;\n  line-height: 20px; }\n\n.avatar_3zs {\n  width: 60px;\n  height: 60px;\n  background: transparent url(/img/default-avatar.png) no-repeat center center;\n  background-size: contain;\n  margin: auto 0;\n  border-radius: 30px; }\n\n.guide-info2_3dt {\n  margin: 30px 0; }\n\n.small-info-title_c49 {\n  font-size: 18px;\n  font-size: 1.125rem;\n  font-weight: 900;\n  line-height: 25px; }\n\n.small-info-content_1xA {\n  font-size: 14px;\n  font-size: 0.875rem;\n  line-height: 25px; }\n\n.self-intro_3CW {\n  padding: 0 10px 20px;\n  text-align: left; }\n"
    },
    "./common/components/custom/PhaseDeposit/styles.scss": {
      "container": "container_s0_",
      "_style": "/* stylelint-disable */\n/* stylelint-enable */\n/* stylelint-disable */\n/* stylelint-enable */\n.container_s0_ {\n  height: 300px;\n  padding: 0 15px;\n  text-align: center; }\n"
    },
    "./common/components/forms/custom/ChooseDateTimeForm/styles.scss": {
      "choose-item": "choose-item_3lM",
      "chooseItem": "choose-item_3lM",
      "choose-item-inner": "choose-item-inner_280",
      "chooseItemInner": "choose-item-inner_280",
      "form-group": "form-group_29U",
      "formGroup": "form-group_29U",
      "add-btn": "add-btn_4uM",
      "addBtn": "add-btn_4uM",
      "footer": "footer_373",
      "btn-trash": "btn-trash_283",
      "btnTrash": "btn-trash_283",
      "btn-submit": "btn-submit_2m8",
      "btnSubmit": "btn-submit_2m8",
      "_style": "/* stylelint-disable */\n/* stylelint-enable */\n/* stylelint-disable */\n/* stylelint-enable */\n.choose-item_3lM {\n  display: -webkit-box;\n  display: -ms-flexbox;\n  display: flex;\n  -webkit-box-orient: horizontal;\n  -webkit-box-direction: normal;\n      -ms-flex-direction: row;\n          flex-direction: row;\n  -webkit-box-align: center;\n      -ms-flex-align: center;\n          align-items: center;\n  margin: 10px 0; }\n\n.choose-item-inner_280 {\n  display: -webkit-box;\n  display: -ms-flexbox;\n  display: flex;\n  -webkit-box-orient: horizontal;\n  -webkit-box-direction: normal;\n      -ms-flex-direction: row;\n          flex-direction: row;\n  -webkit-box-align: center;\n      -ms-flex-align: center;\n          align-items: center;\n  -webkit-box-flex: 1;\n      -ms-flex: 1;\n          flex: 1; }\n\n.form-group_29U {\n  margin: 0 !important;\n  padding: 0 5px !important; }\n\n.add-btn_4uM {\n  font-size: 16px;\n  font-size: 1rem;\n  float: right;\n  margin-top: 20px;\n  color: #f78b6d;\n  border: 0;\n  background: transparent; }\n  .add-btn_4uM:focus {\n    outline: 0; }\n\n.footer_373 {\n  margin-top: 80px;\n  text-align: center; }\n\n.btn-trash_283 {\n  font-size: 18px !important;\n  font-size: 1.125rem !important;\n  width: 30px !important;\n  height: 30px !important;\n  background-color: #aaaaaa !important; }\n\n.btn-submit_2m8 {\n  margin: 0 auto; }\n"
    },
    "./common/components/custom/PhaseChooseDate/styles.scss": {
      "container": "container_1C_",
      "guide-info": "guide-info_kdR",
      "guideInfo": "guide-info_kdR",
      "_style": "/* stylelint-disable */\n/* stylelint-enable */\n/* stylelint-disable */\n/* stylelint-enable */\n.container_1C_ {\n  padding: 0 15px;\n  text-align: center; }\n\n.guide-info_kdR {\n  display: -webkit-box;\n  display: -ms-flexbox;\n  display: flex;\n  -webkit-box-orient: vertical;\n  -webkit-box-direction: normal;\n      -ms-flex-direction: column;\n          flex-direction: column;\n  position: relative;\n  width: 100%;\n  margin-top: 20px;\n  padding: 20px;\n  border: 0;\n  background-color: #ffffff;\n  box-shadow: 3px 3px 8px 0 #cccccc; }\n"
    },
    "./common/components/custom/PhaseFinishConfirm/styles.scss": {
      "container": "container_2u6",
      "choose-div": "choose-div_1Da",
      "chooseDiv": "choose-div_1Da",
      "comment": "comment_eu4",
      "p-comment": "p-comment_2A0",
      "pComment": "p-comment_2A0",
      "img-again": "img-again_38C",
      "imgAgain": "img-again_38C",
      "img-ok": "img-ok_1EZ",
      "imgOk": "img-ok_1EZ",
      "btn-again": "btn-again_2Ll",
      "btnAgain": "btn-again_2Ll",
      "_style": "/* stylelint-disable */\n/* stylelint-enable */\n/* stylelint-disable */\n/* stylelint-enable */\n.container_2u6 {\n  display: -webkit-box;\n  display: -ms-flexbox;\n  display: flex;\n  -webkit-box-orient: horizontal;\n  -webkit-box-direction: normal;\n      -ms-flex-direction: row;\n          flex-direction: row;\n  -webkit-box-align: stretch;\n      -ms-flex-align: stretch;\n          align-items: stretch;\n  padding: 0 15px;\n  text-align: center; }\n\n.choose-div_1Da {\n  display: -webkit-box;\n  display: -ms-flexbox;\n  display: flex;\n  -webkit-box-orient: vertical;\n  -webkit-box-direction: normal;\n      -ms-flex-direction: column;\n          flex-direction: column;\n  -webkit-box-pack: justify;\n      -ms-flex-pack: justify;\n          justify-content: space-between;\n  -webkit-box-flex: 1;\n      -ms-flex: 1;\n          flex: 1;\n  -webkit-box-align: center;\n      -ms-flex-align: center;\n          align-items: center; }\n\n.comment_eu4 {\n  width: 90%;\n  margin: 30px 0; }\n\n.p-comment_2A0 {\n  line-height: 25px; }\n\n.img-again_38C {\n  width: 100px;\n  height: 100px;\n  background: transparent url(/img/custompage/zoom.png) no-repeat center center;\n  background-size: contain; }\n\n.img-ok_1EZ {\n  width: 100px;\n  height: 100px;\n  background: transparent url(/img/custompage/finish.png) no-repeat center center;\n  background-size: contain; }\n\n.btn-again_2Ll {\n  background-color: #1090ff; }\n"
    },
    "./common/components/custom/PhaseBalance/styles.scss": {
      "container": "container_1xM",
      "_style": "/* stylelint-disable */\n/* stylelint-enable */\n/* stylelint-disable */\n/* stylelint-enable */\n.container_1xM {\n  height: 300px;\n  padding: 0 15px;\n  text-align: center; }\n"
    },
    "./common/components/custom/PhaseTravel/styles.scss": {
      "container": "container_AOj",
      "comment": "comment_U8C",
      "postcard": "postcard_KtO",
      "postcard-title": "postcard-title_30S",
      "postcardTitle": "postcard-title_30S",
      "postcard-stamp": "postcard-stamp_3qi",
      "postcardStamp": "postcard-stamp_3qi",
      "postcard-pic": "postcard-pic_Dkc",
      "postcardPic": "postcard-pic_Dkc",
      "btn-div": "btn-div_2HZ",
      "btnDiv": "btn-div_2HZ",
      "_style": "/* stylelint-disable */\n/* stylelint-enable */\n/* stylelint-disable */\n/* stylelint-enable */\n.container_AOj {\n  padding: 0 15px;\n  text-align: center; }\n\n.comment_U8C {\n  font-size: 16px;\n  font-size: 1rem;\n  margin-bottom: 30px; }\n\n.postcard_KtO {\n  position: relative;\n  width: 100%;\n  height: 385px;\n  padding: 15px;\n  background-color: #fdf9f3;\n  box-shadow: 3px 3px 8px 0 #cccccc; }\n\n.postcard-title_30S {\n  width: 260px;\n  height: 70px;\n  background: transparent url(/img/custompage/postcard-title.png) no-repeat center center;\n  background-size: contain;\n  position: relative;\n  top: -5px;\n  margin: 0 auto; }\n\n.postcard-stamp_3qi {\n  width: 160px;\n  height: 100px;\n  background: transparent url(/img/custompage/postcard-stamp.png) no-repeat center center;\n  background-size: contain;\n  position: absolute;\n  top: 0;\n  right: 0; }\n\n.postcard-pic_Dkc {\n  width: 100%;\n  height: 285px;\n  background: transparent url(/img/custompage/vinis.jpg) no-repeat center center;\n  background-size: cover; }\n\n.btn-div_2HZ {\n  margin-top: 50px; }\n"
    },
    "./common/components/forms/custom/AdviceForm/styles.scss": {
      "footer": "footer_n5F",
      "btn-submit": "btn-submit_1_K",
      "btnSubmit": "btn-submit_1_K",
      "_style": "/* stylelint-disable */\n/* stylelint-enable */\n/* stylelint-disable */\n/* stylelint-enable */\n.footer_n5F {\n  margin-top: 30px;\n  text-align: center; }\n\n.btn-submit_1_K {\n  margin: 0 auto; }\n"
    },
    "./common/container/custom/MyCustomTripPhasePage/styles.scss": {
      "btn-confirm": "btn-confirm_1RQ",
      "btnConfirm": "btn-confirm_1RQ",
      "main-panel": "main-panel_3IS",
      "mainPanel": "main-panel_3IS",
      "finish-panel": "finish-panel_VYS",
      "finishPanel": "finish-panel_VYS",
      "panel-title": "panel-title_3HB",
      "panelTitle": "panel-title_3HB",
      "_style": "/* stylelint-disable */\n/* stylelint-enable */\n/* stylelint-disable */\n/* stylelint-enable */\n.btn-confirm_1RQ {\n  margin: 45px auto 5px; }\n\n.main-panel_3IS {\n  padding: 20px 5px; }\n\n.finish-panel_VYS {\n  font-size: 20px;\n  font-size: 1.25rem;\n  padding: 20px 5px;\n  background-color: transparent; }\n\n.panel-title_3HB {\n  color: #f78b6d !important; }\n"
    },
    "./common/container/homepage/styles.scss": {
      "jumbotron": "jumbotron_1cm",
      "company-name": "company-name_zRZ",
      "companyName": "company-name_zRZ",
      "company-slogan": "company-slogan_1-e",
      "companySlogan": "company-slogan_1-e",
      "produce-trip": "produce-trip_12A",
      "produceTrip": "produce-trip_12A",
      "produce-trip-button": "produce-trip-button_r9B",
      "produceTripButton": "produce-trip-button_r9B",
      "product-feature": "product-feature_14h",
      "productFeature": "product-feature_14h",
      "product-feature-headline": "product-feature-headline_2wJ",
      "productFeatureHeadline": "product-feature-headline_2wJ",
      "features": "features_1fO",
      "feature": "feature_CIJ",
      "feature-headline": "feature-headline_37L",
      "featureHeadline": "feature-headline_37L",
      "feature-intro": "feature-intro_3dx",
      "featureIntro": "feature-intro_3dx",
      "hr": "hr_2PV",
      "img": "img_uXG",
      "user-reviews": "user-reviews_-uc",
      "userReviews": "user-reviews_-uc",
      "user-reviews-headline": "user-reviews-headline_1dG",
      "userReviewsHeadline": "user-reviews-headline_1dG",
      "posts": "posts_2FB",
      "post": "post_2-y",
      "_style": "/* stylelint-disable */\n/* stylelint-enable */\n/* stylelint-disable */\n/* stylelint-enable */\n.jumbotron_1cm {\n  display: -webkit-box;\n  display: -ms-flexbox;\n  display: flex;\n  -webkit-box-orient: vertical;\n  -webkit-box-direction: normal;\n      -ms-flex-direction: column;\n          flex-direction: column;\n  -webkit-box-align: center;\n      -ms-flex-align: center;\n          align-items: center;\n  width: 100%;\n  height: 100%;\n  background: transparent url(/img/homepage/river_dark.jpg) no-repeat center center;\n  background-size: cover;\n  -webkit-box-pack: start;\n      -ms-flex-pack: start;\n          justify-content: flex-start;\n  min-height: 100vh;\n  margin-bottom: 0 !important; }\n\n.company-name_zRZ {\n  font-size: 60px !important;\n  font-size: 3.75rem !important;\n  padding-top: 35vh;\n  color: white; }\n\n.company-slogan_1-e {\n  font-size: 20px;\n  font-size: 1.25rem;\n  padding-bottom: 40px;\n  color: white; }\n\n.produce-trip_12A {\n  padding-top: 13px;\n  color: white; }\n\n.produce-trip-button_r9B {\n  padding: 1px 40px;\n  border: none;\n  border-radius: 300px;\n  background-color: #ff7744; }\n\n.product-feature_14h {\n  height: 45vh;\n  background-color: #fffaf0; }\n\n.product-feature-headline_2wJ {\n  display: -webkit-box;\n  display: -ms-flexbox;\n  display: flex;\n  -webkit-box-orient: vertical;\n  -webkit-box-direction: normal;\n      -ms-flex-direction: column;\n          flex-direction: column;\n  -webkit-box-align: center;\n      -ms-flex-align: center;\n          align-items: center;\n  -webkit-box-pack: start;\n      -ms-flex-pack: start;\n          justify-content: flex-start;\n  padding-top: 5vh;\n  font-size: 1.5vw;\n  font-weight: bold; }\n\n.features_1fO {\n  display: -webkit-box;\n  display: -ms-flexbox;\n  display: flex;\n  -webkit-box-orient: horizontal;\n  -webkit-box-direction: normal;\n      -ms-flex-direction: row;\n          flex-direction: row;\n  -webkit-box-pack: center;\n      -ms-flex-pack: center;\n          justify-content: center; }\n\n.feature_CIJ {\n  display: -webkit-box;\n  display: -ms-flexbox;\n  display: flex;\n  -webkit-box-orient: vertical;\n  -webkit-box-direction: normal;\n      -ms-flex-direction: column;\n          flex-direction: column;\n  -webkit-box-align: center;\n      -ms-flex-align: center;\n          align-items: center;\n  -webkit-box-pack: start;\n      -ms-flex-pack: start;\n          justify-content: flex-start;\n  width: 20vw; }\n\n.feature-headline_37L {\n  padding-bottom: 5px;\n  font-size: 20px;\n  font-weight: bold; }\n\n.feature-intro_3dx {\n  width: 175px;\n  line-height: 1.5em;\n  text-align: center; }\n\n.hr_2PV {\n  display: block;\n  width: 2%;\n  border-width: 3px;\n  border-color: #ff7744; }\n\n.img_uXG {\n  width: 30%;\n  padding-bottom: 1vh; }\n\n.user-reviews_-uc {\n  width: 100%;\n  height: 100%;\n  background: transparent url(/img/homepage/night.jpg) no-repeat center center;\n  background-size: cover;\n  min-height: 70vh;\n  background-size: 100%; }\n\n.user-reviews-headline_1dG {\n  padding-bottom: 5px;\n  font-size: 20px;\n  font-weight: bold; }\n\n.posts_2FB {\n  display: -webkit-box;\n  display: -ms-flexbox;\n  display: flex;\n  -ms-flex-wrap: wrap;\n      flex-wrap: wrap;\n  -webkit-box-pack: center;\n      -ms-flex-pack: center;\n          justify-content: center;\n  padding: 30px; }\n\n.post_2-y {\n  padding: 5px; }\n"
    },
    "./public/img/homepage/icon01.png": "/js/1_e-ORp",
    "./public/img/homepage/icon02.png": "/js/2rpdBDw",
    "./public/img/homepage/icon03.png": "/js/FJ2bHsv"
  }
}